[{"resource_state": 2, "athlete": {"id": 4495383, "resource_state": 1}, "name": "My giro d\u2019Italia tappa 20: Z\u00fcrich - Freiburg", "distance": 142583.0, "moving_time": 19471, "elapsed_time": 23041, "total_elevation_gain": 2178.0, "type": "Ride", "sport_type": "Ride", "workout_type": 10, "id": 11604996305, "start_date": "2024-06-08T09:35:32Z", "start_date_local": "2024-06-08T11:35:32Z", "timezone": "(GMT+01:00) Europe/Zurich", "utc_offset": 7200.0, "location_city": null, "location_state": null, "location_country": "Germany", "achievement_count": 110, "kudos_count": 10, "comment_count": 2, "athlete_count": 1, "photo_count": 0, "map": {"id": "a11604996305", "summary_polyline": "up``Hgwes@rBfLst@h^aGnNwLzEmo@}Cob@jC_x@p\\y]cKwcAh_AoZ`c@kVpiAmM{NoMnIaJt[fEzJgRjaAuo@rrAgpAzkBmm@uDeb@hOsr@hDaPfKgKp^kQtG}a@cf@qH}R{ReB{h@_u@}J]cDdCuBrs@iWp^mEVeC`Xug@rKwn@wCecAl~@eUb_Amk@rcAeTd~@sKnP{m@rKik@gGkZjCyZqRgEw\\_Of|@sLjKoUGkIr\\nDxb@zSfZr_@`S~G|WoSltBx@nQ{IhiAuAb~AcGlaA_JtVgz@`jArBfHmVlX}IeRuPmDuKbJy\\`DeQbNib@uBcSxb@eXXwMvHaFnJhBlfAcCxk@iMtl@mC`k@ko@vRgm@bZmJpMec@tOi\\~BeTeBcZdyAsK`SuBjZiWnl@mTnK_@fToJde@aRdi@mFj_@wJ|PsJruBcBqJyKyAvB||@fEjSeTji@mSxR?n|@dG`T{Jtd@lFv\\kCpS`SbLzTh^d^hHvHdQrUsApQpLp@dMfLnN{@bIzIpIqBnZgCxCqJaGsG~NuxAbc@aMpKjBbkAuo@`wAkAlQkTne@mUvHa^~PmVdXcs@t\\mEtHy_@~Es]rRg@{FvMsLyEu`@gSkByYqf@VuTqEuW}E{H}K_@A}G{GiIbCyK_Am[ow@xC_DwIlHuXcNe]kTcQqV}mAgD{`AbCi^al@m_AxFiZcC{Zq{@zq@iRb\\e\\rSmc@jpAyc@`b@uVb{@?~`@{Nz\\b@lRwKl]dBbVuTdrA{PzNeH|m@yKfR{PxKaQti@tBzNrJdAbKhN_AtOpFjm@~M|RbE|e@YnUwH|F}E~OqJvDvKnH`FuFfI|TjQtL`G`Qx]|X|CjZh_@fUzH|PrUyIeJ`NoPjFoAvO{MlLyDdS}MjNmA|HiT|X}L`JuPxE}Kxi@~BdQcExYgj@wJyGyHo{AgZkYfTqc@rLiMkD}Snx@~Bca@_Sjq@yb@fOqRh_@aNdD}^iMyMfOq`@xAyQtViPtGuMhd@mKjC}CzOkLvIeGnTeLfC}O`[c[Cqy@~^ed@ad@yFrLeNc`@_JrPsJg@gRhMtTkGhRW|BnPaIlM`B|NxEbI|GaJdF|EwFYwI~UmNwJyOlaAqJi_@bF}UkAeKoQvO{Hn\\iNlNoBkD|EoVw@iIqWjCkJm\\wDvBh@pLiGfb@_RpJiQkQyBuRsBnUfErV{DjOshAbS{u@xIe]dg@yJda@sWvSsaARxAuQ", "resource_state": 2}, "trainer": false, "commute": false, "manual": false, "private": false, "visibility": "everyone", "flagged": false, "gear_id": null, "start_latlng": [47.36, 8.55], "end_latlng": [47.99, 7.84], "average_speed": 7.323, "max_speed": 19.103, "average_temp": 19, "has_heartrate": true, "average_heartrate": 73.0, "max_heartrate": 73.0, "heartrate_opt_out": false, "display_hide_heartrate_option": true, "elev_high": 1206.6, "elev_low": 275.2, "upload_id": 12384983602, "upload_id_str": "12384983602", "external_id": "garmin_ping_346368542781", "from_accepted_tag": false, "pr_count": 19, "total_photo_count": 5, "has_kudoed": false}, {"resource_state": 2, "athlete": {"id": 4495383, "resource_state": 1}, "name": "My Giro d\u2019Italia tappa 19: Celerina - Z\u00fcrich", "distance": 193162.0, "moving_time": 25254, "elapsed_time": 33019, "total_elevation_gain": 1689.0, "type": "Ride", "sport_type": "Ride", "workout_type": 10, "id": 11596897566, "start_date": "2024-06-07T07:20:04Z", "start_date_local": "2024-06-07T09:20:04Z", "timezone": "(GMT+01:00) Europe/Zurich", "utc_offset": 7200.0, "location_city": null, "location_state": null, "location_country": "Germany", "achievement_count": 82, "kudos_count": 13, "comment_count": 0, "athlete_count": 1, "photo_count": 0, "map": {"id": "a11596897566", "summary_polyline": "mp{zGywd{@mCwKqm@v@ky@gc@yDwPw\\kPcXsh@e[aSqNmUw^kPv@qQot@mpAy`@c\\chA}wAkMaBR~_@gPoI|DlSmHyFlH`{@mFkBPfSsDkUNpZqTrj@kJtn@{@lg@l@pfAnLjrAsB|Kp[j{BlXf_AeDj~@lChSvMpQ[`f@|DlL}LpNmL_FmOxSmAx_BeLtXk@ie@qDxZgRxQqMh_@Dtf@cFtWoO|DnFjHkX~SiZrIgs@qVk^PuQt^u}@xn@}EgDsRzOoSl`@eHf^c\\{AiIdVeVfq@mj@xk@u[psAm[za@_h@dh@yI`[wC`nAiM`KbSzs@lNbiAxG|Kc@~p@~Kpw@_DpQyHvO{@cQiItCmKoN`VthA_Mzw@rLve@vB|^wE~m@lInXqY~iA_GxMyQlWwVOsYlXiXvAe}@d_@sm@wN{jCbPeFxFtFfTgy@|q@yy@yo@rAkPyc@mHw[_Zo[ng@ub@zDiMmHcYjQkLvNuI~c@ce@|LqLbYyn@d`@em@fJq`@wL}t@o@wj@oe@{f@cGeXtNe\\oAsZhYtGk^sWpn@mHn@Ix[iHoO{_@__@oxBNgrA_c@iaAqh@u\\eh@{b@m[wyAk`@gnAi@bDtMwEnRutBlNgPbKkbBlCmChZs_DvvEwc@`oA{i@be@qWbFq`@rg@gL|g@um@b{Asd@jy@_|@ftAaHdDiWnfAnC|Ly^rrAtBfJgxA~rEkrBxqCut@pl@yjA`mBwJfLeHsB}m@njAgFq@kB~k@~]bvAgAzi@xJpPhCxi@aRpxAbHl|@wCkDxIlVnFfl@lEb|BkBr_@kIxNpBhpAoQdfBfFlYcFnGmGxcAyN~k@w@no@{Gj@kEhaAqVfpAhC`yAqHf^sAzfBoExTa[dChMf|CeeAffBolAnOee@lo@}IwXqIlEw[qa@cP_Emq@`b@mb@ph@_qAzn@_Zb_@`EjfAsJz^}zBrfDv_@t~@cLjYErP}IR`@fQnIj@_@xb@yLxDoMve@kI|}DdYlsAxYlhC{VxcBgq@hp@gCrcByGb@cEd`BuI|d@{ThRI~ZcNxz@`DdhBzN~\\rMnrAy@bfDzDnZ_YriA_I`{@sOpXcWvJkSdnA}Onh@uTvYeu@~~CkErv@yMpVMzs@yMhOyEhl@{h@fwAaaB`iBcXzBeQn\\md@rX_k@vp@sz@bUwZnXkq@vYgr@jN}dAvkA}IoF", "resource_state": 2}, "trainer": false, "commute": false, "manual": false, "private": false, "visibility": "everyone", "flagged": false, "gear_id": null, "start_latlng": [46.51, 9.86], "end_latlng": [47.36, 8.56], "average_speed": 7.649, "max_speed": 21.592, "average_temp": 23, "has_heartrate": true, "average_heartrate": 72.0, "max_heartrate": 72.0, "heartrate_opt_out": false, "display_hide_heartrate_option": true, "elev_high": 2313.0, "elev_low": 405.6, "upload_id": 12376647292, "upload_id_str": "12376647292", "external_id": "garmin_ping_346135626029", "from_accepted_tag": false, "pr_count": 58, "total_photo_count": 5, "has_kudoed": false}, {"resource_state": 2, "athlete": {"id": 4495383, "resource_state": 1}, "name": "My Giro d\u2019Italia tappa 18 K\u00f6nigsetappe: Iseo - Celerina", "distance": 173140.0, "moving_time": 27021, "elapsed_time": 31365, "total_elevation_gain": 3830.0, "type": "Ride", "sport_type": "Ride", "workout_type": 10, "id": 11589111141, "start_date": "2024-06-06T07:26:04Z", "start_date_local": "2024-06-06T09:26:04Z", "timezone": "(GMT+01:00) Europe/Rome", "utc_offset": 7200.0, "location_city": null, "location_state": null, "location_country": "Germany", "achievement_count": 0, "kudos_count": 13, "comment_count": 0, "athlete_count": 1, "photo_count": 0, "map": {"id": "a11589111141", "summary_polyline": "e|zuGgvs|@uMkRap@c\\ukBkNko@vf@mE`a@aObTu^xSoj@Pkg@|TkbAxjAcy@|l@uZdEo_@kZag@i@_FaIpEwf@ibAeeC{WmUqu@uDmXaj@uZcUoOka@k{Ac{@uwEejFw\\{MkQgb@o`@o\\zDkCoE}Mkk@wa@_IhS}YcWea@aKuj@qu@ui@ez@eLac@kPqR}{@ouBin@wc@gJid@w_@ax@l@{r@qQcs@co@gDsUad@_CkWhGcHhOak@eZ}o@gOup@mc@s]izAcj@i\\cm@qx@oi@cQaA}Oq[gSgJsl@tDc`@a[{`@nTgn@eJea@`B}RbNutB_m@gjBdFmt@dTsPpV{Hn`@bEd{@yHtv@mr@~[it@hHcYgGsIbLox@mj@acBahBerAgv@gl@_HmKsOgY}Hma@fF}o@~lAye@pSehAm`AkZyGeq@kNox@qW|_@fTbDpT}CaIsErYwCsH{DfN~BaTiFrKa@xv@aV~j@iHtElH}d@eC}[kFqElHgb@{T`_@~Edo@kd@nc@er@jZmLmEek@xJiPzEoGpFDzMoNlGeDdUlJ|TzAzm@zN`PeKQ~Ejd@nDtGon@Fgm@}WuPdD}A`I_MiKkHhAeIjOcItWeu@nH_s@yFig@wd@vi@`gAcm@_e@dEjOwLeI~KdS}M{Hc]}a@F}O_OsZaShK~PhTc@~VfGtT~ImA|`AdsAbBhF}GjL|a@|f@vvAfUv}@|a@`RkVpiAnn@h}@~dAnb@jaAhBp{AxRniAlWjr@~|@peAuErd@sJnMyI|{Ay[dSmXhf@wh@vV_y@naAodAh`@eVuFgWjs@sm@~h@mKnV_VlaBat@dbAqb@lX}e@nCgu@di@oGbUuNrKcj@`]yx@zQE|GmcAi^el@|C_I{GsCeUw_@mTwVah@_`@oSue@~No}@no@i`@m`@oUcE{Hy`@uWe@yTbd@jFlb@sLaOwGbEjFnKsK`GdK~Bcx@VmHbYeYjRuDxWbIpGz@jRwGoKmIjAV|OuRxKrFnIwEtVlJ`T{VoLdZrp@rCz}@ad@dIzE~d@wL`P}Lfr@caA|]o`@bVee@b}@qCr|@qWby@oLrx@eU|\\aHfb@uYbYnGMiBpDqaAljA{bAjw@{tA~tCue@ne@gl@lYoa@bl@iBpb@lKv|@eMrX", "resource_state": 2}, "trainer": false, "commute": false, "manual": false, "private": false, "visibility": "everyone", "flagged": false, "gear_id": null, "start_latlng": [45.69, 10.1], "end_latlng": [46.51, 9.86], "average_speed": 6.408, "max_speed": 22.953, "average_temp": 25, "has_heartrate": false, "heartrate_opt_out": false, "display_hide_heartrate_option": false, "elev_high": 2331.2, "elev_low": 184.8, "upload_id": 12368674559, "upload_id_str": "12368674559", "external_id": "garmin_ping_345899777550", "from_accepted_tag": false, "pr_count": 0, "total_photo_count": 5, "has_kudoed": false}, {"resource_state": 2, "athlete": {"id": 4495383, "resource_state": 1}, "name": "My Giro d\u2019Italia tappa 17: Lodrino - Iseosee", "distance": 36084.7, "moving_time": 5399, "elapsed_time": 6480, "total_elevation_gain": 394.0, "type": "Ride", "sport_type": "Ride", "workout_type": 10, "id": 11580848858, "start_date": "2024-06-05T11:15:08Z", "start_date_local": "2024-06-05T13:15:08Z", "timezone": "(GMT+01:00) Europe/Rome", "utc_offset": 7200.0, "location_city": null, "location_state": null, "location_country": "Germany", "achievement_count": 0, "kudos_count": 9, "comment_count": 0, "athlete_count": 1, "photo_count": 0, "map": {"id": "a11580848858", "summary_polyline": "w{_vGyfw}@oA|DaDvCrBy@hEBx@s@h@}ArAw@V{Bp@tBa@zBuDdH[bC]n@c@PiDkC_AUeCZyDbBu@jA{@nEXrCjArEFzChBtCpAtEEvBs@rADt@jAgBRsAoA{KJcAvAeDtAwAf@LAhA}AdGPdBnBlHVxDgBpGj@DtAiDXAD`@sCbGc@C}@gAs@HF|DWr@iAZM`@hBrD?nAqBbHg@h@aAHWp@|BnCpEdJ\\NL_@gC}EEs@ZFfCzDf@lDhDfM_@dIdAzB|FpGSfCNf@|An@v@`AhAjDM~E`@f@X[?wEcBcOL_@\\N`@z@^zAz@zPMtGgAtIaEpNkBbJwBvCsCnKi@vH_C~Bu@zBOtDf@lGG`H[rBqC`Jy@xB}BbDqQxGi@pAEdAj@d@|Di@fBz@pOfXpFjL`B`GfCjDnBlA`GhAxIfGvDr@rAr@vGpL`E`C|E|It[l_@pBbDpBbG~GvZ^~CFfC_AjRlBpS@|PQfBL`J`@rDbCxFjHrIdB~@vVpF|AYrGiD~WkArQcIt}@rFxEe@zFyC|@d@lEfK\\dDG|FqAjIu@vScAxEK~ABvIy@rDOnCfIdaApFza@zDtTLfCe@tLgBrEqDhEO|@DtEXhBvApC@pETjBtEbIn@zCnChGpKfOTfEQzDNrIM`BFz@xA~Bs@`DAhCvCdKf@h@vH`BrBfFbA`AjEMZZgAvL]O\\kG_@g@QT[|HsCxEw@~I}EjRTdGnDTnCnBF`@e@ZsFc@mAb@_B_Aa@v@h@dCbCfCJdDzAOj@Z`F`NExAqBfF~@nGuA`GnBrIsA~Gn@lPn@hd@qAtKuAlD_@hCeChFyD|O_BvNGdE_AtJBrC~DnSnIlBjLqBjAJ~EnFlB`DnEzMvBzCpElD\\rAY^iENo@dBQ|BWVi@{@_CkAwGoAqC_CeEcBq@CsBlAoCOo@[wAeCD|@hAnCrAfAxCbA~@dA~@tCjAhGhAbCBn@]V_@kBeEuDkAeBg@h@eC`G_@TeAuAcCu@{@sA_@EcAhDBtAb@VhA{@~@@|B`DhA^`Aw@r@_Cj@Mz@lGfCjIpAxBrChDzFz@`@j@Uv@{Ak@mEXwH{CcEq@YRHr@hExAZn@Gt@yAjB_BVcDI{Ay@oG_IkEuAmAaAmAiEuBkCmFqKkGsTuDuJ{FgH}HmLmEiEgEoG_@Ee@qBcKqQw@i@mByDuBwH_AqGeCeFuIgLqIeHwFqG{BuFyAaCoAyEqAiB}UuL}A_@Q\\", "resource_state": 2}, "trainer": false, "commute": false, "manual": false, "private": false, "visibility": "everyone", "flagged": false, "gear_id": null, "start_latlng": [45.72, 10.28], "end_latlng": [45.69, 10.1], "average_speed": 6.684, "max_speed": 17.704, "average_temp": 27, "has_heartrate": true, "average_heartrate": 79.0, "max_heartrate": 79.0, "heartrate_opt_out": false, "display_hide_heartrate_option": true, "elev_high": 765.4, "elev_low": 191.0, "upload_id": 12360194198, "upload_id_str": "12360194198", "external_id": "garmin_ping_345657520045", "from_accepted_tag": false, "pr_count": 0, "total_photo_count": 4, "has_kudoed": false}, {"resource_state": 2, "athlete": {"id": 4495383, "resource_state": 1}, "name": "My Giro d_italia tappa 17: Lodrino Hike", "distance": 7343.4, "moving_time": 7882, "elapsed_time": 614262, "total_elevation_gain": 672.0, "type": "Hike", "sport_type": "Hike", "id": 11580845406, "start_date": "2024-06-05T08:15:34Z", "start_date_local": "2024-06-05T10:15:34Z", "timezone": "(GMT+01:00) Europe/Rome", "utc_offset": 7200.0, "location_city": null, "location_state": null, "location_country": "Germany", "achievement_count": 0, "kudos_count": 0, "comment_count": 0, "athlete_count": 1, "photo_count": 0, "map": {"id": "a11580845406", "summary_polyline": "{x`vGa|v}@GXc@f@Wl@QNCUP_AVa@Po@?]Qq@[m@Ic@Wo@EA?BCYA?Mm@@IGa@k@oAc@gCSg@?e@D?K_@AKRk@@a@FGFw@E@Q^]T]Bc@GW~AGDICEk@Do@AOFUJUTKFO@KIG]PIPG?E{@EGK}@BKAy@Di@LYf@{A`AOPGh@g@VIBONEZwAv@YR@RMLMJAPMc@N@FOJo@JKHORAf@CF_@ZOFGJKBi@n@SJUK[PK@KPE^KJWr@[b@GBUEEJKf@JpAENq@z@?FOEEKODCKDO?QBCAIOFII]AODKNI][EL]NSBOI]IKKNYBQLs@RGPIDKf@a@TCRQ@CKEFCMOMMf@KUI_@EJG[EVIFCNAZGCAFMDE_@EO?QKMIg@O[A[gBJLODSG@BGMSBGCC@NQIGKMAS[UOCMI?GfF@JQFK^SPU^?HEBI`@BRGLAVIX@`@KLTjACf@MZAPOj@SVO`@c@VGFIh@@b@En@Ud@On@WZFLLILFJLFVCLDMQj@Cp@[`@c@hAE`ABLFDPADGN@?VMRGEEb@B\\Rj@d@RLf@?HK^Et@KNEc@CPAGABGG@EGDCK?HIGIFGIBACEADSUG`@M[Mp@BTEBAf@D@I?AHGDAGOP_@PS\\_@^SFCFQDW^AJg@b@Yv@Wd@MHc@lAs@bAC`@FXEFFBCj@GRYLPXDb@Nn@A|AP`AP`@ARDb@?l@JjAARKTM`AAZRp@KbAIZUR?JINBBAHFREpAJh@@XEJKbAUJGf@OR?HPFp@GRd@DWVGJKBOC??EVe@j@[XGf@k@BKCSFEGECcAVWDSLSb@_@F[?_@P}@E[B[CKBi@PMH[TYBOE_@H[d@_@XALIFUCi@DSV_@BeABCFH@WVKL_@n@i@LYlAeAl@YF[`@c@`@MFQV]`@c@j@[?p@]jCNdANPDJGp@K^ZK`ACd@KZa@Zk@RKLQNEj@PDH\\x@Fh@JBBs@HYNQPGZYr@{@j@aBjAgBBYJSPm@Ve@`@_@n@Y\\[LaBFi@ZgAFcAj@_FT_@x@m@V[D[HSDJGb@F\\ZiAl@s@`@mBNQb@CROD_@Jc@?UBUVqAd@DJPXzDFb@BBNMLYJGb@@n@`@n@|@ZXtAx@XBjAKd@SJKLa@h@_@", "resource_state": 2}, "trainer": false, "commute": false, "manual": false, "private": false, "visibility": "followers_only", "flagged": false, "gear_id": null, "start_latlng": [45.72, 10.28], "end_latlng": [45.72, 10.28], "average_speed": 0.932, "max_speed": 7.464, "average_cadence": 56.4, "average_temp": 27, "has_heartrate": true, "average_heartrate": 91.1, "max_heartrate": 114.0, "heartrate_opt_out": false, "display_hide_heartrate_option": true, "elev_high": 1385.4, "elev_low": 761.8, "upload_id": 12360190606, "upload_id_str": "12360190606", "external_id": "garmin_ping_345657449306", "from_accepted_tag": false, "pr_count": 0, "total_photo_count": 0, "has_kudoed": false}, {"resource_state": 2, "athlete": {"id": 4495383, "resource_state": 1}, "name": "My Giro d\u2019Italia tappa 16: Verona - Lodrino", "distance": 151720.0, "moving_time": 21522, "elapsed_time": 35173, "total_elevation_gain": 1650.0, "type": "Ride", "sport_type": "Ride", "workout_type": 10, "id": 11572491666, "start_date": "2024-06-04T06:32:56Z", "start_date_local": "2024-06-04T08:32:56Z", "timezone": "(GMT+01:00) Europe/Rome", "utc_offset": 7200.0, "location_city": null, "location_state": null, "location_country": "Germany", "achievement_count": 0, "kudos_count": 11, "comment_count": 1, "athlete_count": 1, "photo_count": 0, "map": {"id": "a11572491666", "summary_polyline": "gkhtGmrabAsAt]eKrXot@tc@oD~^mkAhlAoKdU{Jjq@JlGbFoBya@t{APlg@gf@npEoCx}@{Dbj@vD`cA}Off@pLfK{Sto@mJ|t@yDbAoLlkAsVbWa`@jKw}@h_AcRzf@oc@hb@k`BdQDfl@uEdgAuP|O}GoAoKdg@iMvSiPuL~ItUsIl]b@|O~G`JfUvAbBxTy`@pVi`@bFaUlb@wB|[eKzHMjGoXrMqDbXrDlPonAvo@oVd]qb@aE_LnEyIdRmEzw@{Kvh@tI`e@d[xk@x@fIaFjEua@fEak@}IuiAy|@klAuLaOgZwiCclAg^aZye@qm@_R}[y`Aqf@ckBcwAce@{k@keAsq@kjA{cAk[kK_bAqhAag@gBmLu_@op@yu@ii@g]mj@~HeFm`@wUyVioA}YouAak@sUeV__@g`A{VcXyS}Am_@qs@gZwb@woBy_@{a@{QsNtDeq@iYkc@nBeiAqsA}MfGgRuJsS|D{b@ha@aErTtCvz@wYrNpJdKgW`BuQrm@bFhChArb@pa@xEvLsEha@dLCG|DhW`KaItf@fLe@pMaAu@MqL_@`K~B|J}D`DmMpu@hEnTqHduBh@~e@tBYkOb`@R~QiGcEy@wMiHdWsDfPu@rFdBr[cKte@gG|DaJqP}HnCkEpT`FpGwFfDkIz^vDpNo@`Sc[fb@{KdaAqr@x_Bq@ni@`K~\\rGxhAaG|vAtDt_@|\\|k@r}@vp@zi@nnAtd@nVjb@rp@z[nDfYxUrKld@nIvRpSvQiAjEqI~kAG~d@h@rLnQ~^qCw@rL}BpBx_@y@dViAxP{@dGeDuLe]hKoLrXnCaBrGdVda@to@ds@`Ttb@~g@vKlBzk@fh@lEnM_@dNqd@bz@aKdc@lVdQh}Ap~Bdg@jUpIaC`f@lYzn@gDzN}Mba@sCnT~Mf`@rt@z^pL~l@~w@b_@rPxQ~R~c@vg@fJ|`@jPfJnPng@sItTg@xR{[pWlGll@|T~Pr]SjQdM~aArhBnRzSzKp_@~N`LpLz[zNnbAfOj]oIjUzLl_@|@b\\sChm@wGjW]|a@dYh~@n@f]zQpx@nFh}@sRhUyEjEnKqXmAaTi@vJ{BrEcFmLqCfJq@sFcPdB|KjHkFnMgF|MuFpFjD~McHtVxAzHeEtIiKnH`F~P[`F_Q|QgA~PoPtWlBnMoPhNwC`QeJnA|EcG", "resource_state": 2}, "trainer": false, "commute": false, "manual": false, "private": false, "visibility": "everyone", "flagged": false, "gear_id": null, "start_latlng": [45.43, 10.99], "end_latlng": [45.72, 10.28], "average_speed": 7.05, "max_speed": 14.492, "average_temp": 19, "has_heartrate": true, "average_heartrate": 72.0, "max_heartrate": 72.0, "heartrate_opt_out": false, "display_hide_heartrate_option": true, "elev_high": 766.8, "elev_low": 60.0, "upload_id": 12351623333, "upload_id_str": "12351623333", "external_id": "garmin_ping_345402230976", "from_accepted_tag": false, "pr_count": 0, "total_photo_count": 5, "has_kudoed": false}, {"resource_state": 2, "athlete": {"id": 4495383, "resource_state": 1}, "name": "My Giro d\u2018Italia tappa 15: Cervia - Verona", "distance": 208929.0, "moving_time": 26568, "elapsed_time": 35067, "total_elevation_gain": 232.0, "type": "Ride", "sport_type": "Ride", "workout_type": 10, "id": 11566443248, "start_date": "2024-06-03T06:14:40Z", "start_date_local": "2024-06-03T08:14:40Z", "timezone": "(GMT+01:00) Europe/Rome", "utc_offset": 7200.0, "location_city": null, "location_state": null, "location_country": "Germany", "achievement_count": 0, "kudos_count": 10, "comment_count": 0, "athlete_count": 1, "photo_count": 0, "map": {"id": "a11566443248", "summary_polyline": "uaemGscljAjQjQjHb[kSbMu@zqA__@vj@ynDnsCmb@fg@cgEhdDe{AzdAis@nPqtA`oAgJtd@mOj\\qJ@i|Ah~Ac^tH{Tj[wT}C}VnK@bj@oTbHoTbi@}FiAmPlgAat@u@qo@rbAHhK_E}EsnA`d@`]hsCqFvxAvHzDaj@rkBorAroCkm@nu@aS~e@kw@~G_b@b[iQ~i@_o@rx@in@bsA_jDznDuLdcArAhQeFxNv@p[eXv`AbYihA~EjL}@~d@eK~y@_YcHeo@jgEbAvRcHjKcf@b{Cs{AhqEsLeBg^xj@yBfz@wN|GkZdc@mRlA}[r^woA|x@ul@v_BoYlNqm@~p@_[lGcNfPes@xlBwf@dYeFfWlDvJuGb{@u]nq@cWzO{YbB}g@b`@kWzEkOps@iKnOqCfXskAtMyh@zc@yExc@mL|^gGx{@wJz@qAtLig@oGJ`g@{HjM}UbEcLvQcFdy@}GjMaOdB}i@mF}H~m@a{@`zBqe@bWe{@yKmVnHmfAb{A}Xj{@ifAjNcFvW_MxR{OaCi\\wo@ae@k`@kyAtdAgg@~m@m`@{d@__@uApBxU_Ull@mKbH_Ef_@eKjVo}AuS_XtFca@iC}~@{n@iObL_^qEgc@hvAqQhSktAoDqUfq@cVth@gEhl@oIbPwAtZqM~a@gh@nd@_Xbh@{c@vlCoXta@uH`^|OfkAvV|^vDh[`GrcCb[~gCaGvmAqI|QqZrPgjBeYya@fL{PzW{UhmAgNjeApAbXc]boB}d@rjAeNt{@_h@zpAqQzUqFblA{w@|gAui@vf@uRdb@u_@|XnCnh@cFnn@pCzh@eDva@{tApq@cd@o[u^oGgaApM}LrT_Hpu@fAtb@ikAzRcHns@e`BuOmgEroAgsE`Jc]gl@u_@lf@k\\pLwZzb@a^zVm~@xUch@jj@sl@f]ub@bg@~NiR~LiNkBeN}QmN_a@pFoSwEsv@heAgd@hPs`Apq@{UePeQdZe~@ea@qQ~Av@vQcE|J}V{S_RjTs}A{a@`CjCgBaPeg@mo@yWbf@wXdmByXiTySiDwKtJ{b@``BsH~EkQxx@uj@cYqU~J`W}D_vBl{J_aAhkAcRh_@i[dGiCjYeb@h`@s`@hs@aSfNs]vcA{_ApjAuvBzgEeEy@`C|EkOld@wY~Yiu@id@wLo@oFnV", "resource_state": 2}, "trainer": false, "commute": false, "manual": false, "private": false, "visibility": "everyone", "flagged": false, "gear_id": null, "start_latlng": [44.27, 12.36], "end_latlng": [45.43, 10.99], "average_speed": 7.864, "max_speed": 12.24, "average_temp": 23, "has_heartrate": false, "heartrate_opt_out": false, "display_hide_heartrate_option": false, "elev_high": 65.4, "elev_low": -0.1, "upload_id": 12345387659, "upload_id_str": "12345387659", "external_id": "garmin_ping_345208286687", "from_accepted_tag": false, "pr_count": 0, "total_photo_count": 7, "has_kudoed": false}, {"resource_state": 2, "athlete": {"id": 4495383, "resource_state": 1}, "name": "My Giro d\u2018Italia tappa 14: Urbania - Cervia", "distance": 108776.0, "moving_time": 15991, "elapsed_time": 28864, "total_elevation_gain": 1419.0, "type": "Ride", "sport_type": "Ride", "workout_type": 10, "id": 11552796152, "start_date": "2024-06-01T07:10:57Z", "start_date_local": "2024-06-01T09:10:57Z", "timezone": "(GMT+01:00) Europe/Rome", "utc_offset": 7200.0, "location_city": null, "location_state": null, "location_country": "Germany", "achievement_count": 0, "kudos_count": 7, "comment_count": 0, "athlete_count": 1, "photo_count": 0, "map": {"id": "a11552796152", "summary_polyline": "q_oiG}skkAwIsOqQ|KoGePcIpI}AuZeVsIiO`OcTlIoRhh@iFbABbHaFxMaDpBDhDeLvGN`LsF_@}CiEwLnD{CzH?hHaGpEuBlKjE|U}Hf^eGtGyC|JjEpSkCdS~CjLe]xOeGnQaFlEVnKeF`\\_EvD|@qGkPrEyIxO}J~E{E~M{Y|d@aAc@vCeK}KzDoNzLgG^{DdImRdJtJpU}CxD}MsKwQaF_Q_AiSjImZ_Tu[CiO{F{Sm@g`@}^cZwMoKcOo_@kF{s@cvAiAqI|CmKE}F_KcVyJkHg_@af@}aAaQoDcJs_@{[kPyAiHqEqDwSaHuCwUnTm@rLcD|DyB`P~@|EaDzLqDhDwAnKc^sGaP}G_BkEcL`F{JwDaA_DsE?}BcFmMvBpEtDiBt@i@`NqBd@{GrP`@dJdIxCyJhK{BbZ_IbB_CfLeCmDwUx@}CjAiN`PpBxN|GfGzDi@|AlFg@~NuCqA{FbHbEjMxDRqDfCmNsNuLnKyVoTiR{H}IiMsFyWcG?mYkUwGqPw@aXcKcHwHaNqNfEfFqG_G}Bu]vM{CrEc@bIyJdH{DoDs@nKyI~FwAwL~CcR_VhHqEtL|HpM_KtF_@bJwN`QyAjLsTfCqExF_VB{DlIjE|@cGbMiYrCoUfQcRlWoCvKhGtX[lDqd@aPqIdH}j@|G_LhGtL{Ose@nYeA_@rLuL}[rNhEgGyFlC{CxNgN~NjMaGgTlS}DyHzCcPoEfI^eLxCcIkBs@yGrQd@tNiPuPC~SuF~GaJk@NpHq@uGiIsCsMtKqL{C}UzI{DpOsGpBDgI{CeEa[kImJkFjC_AoGkKG}Z{f@sWrFu@kD}CLuZyJm_@kLiDeAtFeRlBsGnGaFd@_c@kKwLoIsh@a{@iPwIkAf]mMxM{HfBya@aAiOn@{M~Bb@~GeDqAi@pCwFqGN|FoBvBqVxIaLp[gPuSk\\_q@gMn`@cH~K}b@fRas@pk@adAhEqTgZeA|JqQzf@mH|t@eRn`@{NpWwj@xm@ez@jm@gMtm@cHzP_GIwDnTcAm@v@oIa_AmcA_DgKyFqEeMhCkSoViEk@q]vHqXuMiUKw^_I{CdAqGfTuBv@stAin@}aAqqAiXb`@e`@`_@mZym@{i@rv@_jAhuAg_@v\\cDeFlDrFvYmWj@_E}CuCdCvGsv@ds@zEoCjTdo@ktArxAuHXObHkWnXuPH{HqEokAn}@wlCztAgFgm@s^xRu\\rHf@lHrRh\\sDnBjD`PcRrKebA{PuVhFkAyL}b@rHkBkH", "resource_state": 2}, "trainer": false, "commute": false, "manual": false, "private": false, "visibility": "everyone", "flagged": false, "gear_id": null, "start_latlng": [43.66, 12.52], "end_latlng": [44.29, 12.35], "average_speed": 6.802, "max_speed": 18.25, "average_temp": 24, "has_heartrate": true, "average_heartrate": 76.7, "max_heartrate": 126.0, "heartrate_opt_out": false, "display_hide_heartrate_option": true, "elev_high": 689.2, "elev_low": -9.6, "upload_id": 12331330413, "upload_id_str": "12331330413", "external_id": "garmin_ping_344824432510", "from_accepted_tag": false, "pr_count": 0, "total_photo_count": 5, "has_kudoed": false}, {"resource_state": 2, "athlete": {"id": 4495383, "resource_state": 1}, "name": "My Giro d\u2018Italia tappa 13a: Monte Porche", "distance": 9020.7, "moving_time": 4090, "elapsed_time": 4183, "total_elevation_gain": 491.0, "type": "Run", "sport_type": "TrailRun", "workout_type": 0, "id": 11538650957, "start_date": "2024-05-31T08:32:45Z", "start_date_local": "2024-05-31T10:32:45Z", "timezone": "(GMT+01:00) Europe/Rome", "utc_offset": 7200.0, "location_city": null, "location_state": null, "location_country": "Germany", "achievement_count": 0, "kudos_count": 3, "comment_count": 0, "athlete_count": 1, "photo_count": 0, "map": {"id": "a11538650957", "summary_polyline": "ausdGchpoA@a@TuA\\}AF}@Ag@McBAc@CaF@q@A{@QsDBa@Ky@OiBU{BGa@Os@S_@UMGCg@Em@?[KGGEQCy@@cDCgBDmD?m@QeCWgB]mBo@}Bm@}Ag@y@{@gAm@i@c@Wq@[]GY@qDr@iABkDAaBDy@Dk@CIGKc@GoAUqAi@cCIo@Ac@BWHWd@g@JGd@MRMJMXc@|AyCd@m@Xk@V]d@aAx@kCP}@RkB@WAs@Gc@Yc@a@_@a@m@UWw@mAwA{A[w@g@\\o@D_@R]LU@_@Je@Fa@GS?YFOHM?UDo@AWE}@e@GA_@WICWWc@KMG]SWUg@We@_@CE?CAB|@g@l@g@HCp@_@JCJGfBg@l@]@Ga@]W[a@a@]g@[Q[[Wk@SuABq@Cu@@QHY?WWYWi@AI?a@Fq@Jk@Dq@b@wANs@LkANo@J_AFw@EuAD_@LaCT_AZc@NKNUJIX[VOT]RMNOZQRE^UREZMzBm@j@YNKRSJQXiAHO^c@f@a@b@s@NM\\SJEPCjAG`@SCB?@e@PqAHa@L[Vm@~@]V[\\OVW~@KTUTo@^o@Ta@HQH_@JULkAZg@XILYReBfBe@r@IZWzDD|@IzAKz@M`@UfBi@xBStAIvABHj@bABJ@NETAX@x@?p@Hp@Pt@PXNN^Td@n@b@^HNJJPLDHCFWNe@RwBj@cAp@s@n@a@RJPd@X~Az@b@Pn@b@j@Z~@^R?VFVITAd@QTA`@Db@CJANM^C\\IXSVEJ@XId@U^v@rA`Br@fAxAhBXd@FXBb@?\\I|@]zBMh@]fAUl@S`@iB|Cq@pA]f@w@~@cAh@YZKXEZA^Fl@z@`DF`@LfBBJVP\\@|BU\\CzBFp@Az@En@EhB]v@I\\@\\Hr@b@VPZ\\n@t@t@jAn@~A|@dD`@`CPnALfCCtC?fADdCCdCFj@LNH@f@?t@DZNZj@H^PlAXzDPxA?z@JpCBbHLpEEx@o@vCKn@", "resource_state": 2}, "trainer": false, "commute": false, "manual": false, "private": false, "visibility": "everyone", "flagged": false, "gear_id": null, "start_latlng": [42.87, 13.2], "end_latlng": [42.87, 13.2], "average_speed": 2.206, "max_speed": 3.517, "average_cadence": 74.9, "average_temp": 15, "has_heartrate": true, "average_heartrate": 120.9, "max_heartrate": 146.0, "heartrate_opt_out": false, "display_hide_heartrate_option": true, "elev_high": 2126.6, "elev_low": 1643.8, "upload_id": 12316741138, "upload_id_str": "12316741138", "external_id": "garmin_ping_344387271402", "from_accepted_tag": false, "pr_count": 0, "total_photo_count": 1, "has_kudoed": false}, {"resource_state": 2, "athlete": {"id": 4495383, "resource_state": 1}, "name": "My Giro d\u2018Italia tappa 13: Castellucio di Norcia - Urbania", "distance": 158491.0, "moving_time": 19396, "elapsed_time": 31137, "total_elevation_gain": 1857.1, "type": "Ride", "sport_type": "Ride", "workout_type": 10, "id": 11679037340, "start_date": "2024-05-31T07:53:33Z", "start_date_local": "2024-05-31T09:53:33Z", "timezone": "(GMT+01:00) Europe/Rome", "utc_offset": 7200.0, "location_city": null, "location_state": null, "location_country": "Germany", "achievement_count": 0, "kudos_count": 0, "comment_count": 0, "athlete_count": 1, "photo_count": 0, "map": {"id": "a11679037340", "summary_polyline": "}hldG_broAch@r[mVbYob@rCc]f`@cW}EuBuNs@fLoDsGwIvM`Ao{@_JyJkQ~C}OtJiN~Wzk@qf@pI?|GtS_Gny@uTkJia@la@mPcLqNxh@wW`WaTlG}E|JUeM{GnXqJye@jCl\\oCtV`QhD_H`ApHnDy\\fGe@vEbHbA{DrFdLpC{`@pa@|HnBqFbClH|Bo]hAnTlOkP{F}RjLkz@fwAuTxk@mZpLsJfVyTbQcIpYgFlo@a]br@uIdx@iLr`@cJ|AiNvYoxAaKu\\hEmP}KcC~LkHuDqrAnl@sUaFgtAjTmk@lg@sFnPkBtj@{\\hi@or@dUgKxOog@wQiNrb@fD~RsArRuIfOom@gGiZgOsZqw@qf@ka@ipA}w@iuAgRkWl@yDbi@gVzh@iAbg@_FdAsNsAwl@i`@{j@|K_q@uJsi@cUeHsL{q@m\\w^pZaAvM{TgImz@zPqMiCaBhZqXzMu`@_`@y`@aNuKJ~AdJoQgCqDdY_l@dJ{bAqVkXi\\g\\xAmc@nVwZeX{[IkTpd@yq@|Kkh@jl@wP~FEnQ{Kb`@_HD|A`RwRd_@uM~L{W|Egr@~l@aj@jD{^aSaUjXmzAhd@ys@dd@iiBrx@ugBbMqPx`@{Gh\\or@fRsVjw@oTtg@_V~IwDmG_Bvj@zDjEK|Kwl@ptAtFjb@nCu@ldA~sB}h@`Ohe@t^uYfh@sOv~BnEh|@oFzr@~Ddn@{IzVSv[mNxUuG|s@cVmC{XoZgJxLeNmGsSvLuj@FqW}Nsn@a|@{oAsi@a][e{@mRwi@f@mb@qYkb@iJmp@rk@oj@zSei@A{YbNwXpq@`Chg@eMt[dEni@wQbVuy@bOi]p[kL``@tAje@iLzt@sMzLmIhh@gJbQbBhEyKvJOeMmDb@Z|l@u[n@kMt_@}\\na@kJtWuHhDaInXK`Vea@wJsHn^Z|UzH~Vw@tMmYlq@vM~kBcMrK_QhbAya@xIcLnQxDfVmEf@}V}V{VnTiNbi@oSrNQtS_Knd@_Xtx@@rK~HrOeCxLizAsWgN{P{XaH{E_Keb@uSqEuKk`Aik@{zAwNq{AtRkEbm@xInwAlKxj@aIzYnEzcAqJ~l@_WvCXd[eSuFpBji@}MmAaa@d[yCt`AkLd_Akj@t_@iI`q@{[`oAgf@fv@aKz@MsJkNjp@ox@pjB~InE_HeIwGjRbFfU|BrS", "resource_state": 2}, "trainer": false, "commute": false, "manual": false, "private": false, "visibility": "everyone", "flagged": false, "gear_id": null, "start_latlng": [42.83, 13.21], "end_latlng": [43.66, 12.52], "average_speed": 8.171, "max_speed": 22.497, "average_temp": 22, "has_heartrate": true, "average_heartrate": 69.0, "max_heartrate": 69.0, "heartrate_opt_out": false, "display_hide_heartrate_option": true, "elev_high": 1654.2, "elev_low": 201.4, "upload_id": 12461263912, "upload_id_str": "12461263912", "external_id": "GOTOES_6448130761015325.gpx", "from_accepted_tag": false, "pr_count": 0, "total_photo_count": 3, "has_kudoed": false}, {"resource_state": 2, "athlete": {"id": 4495383, "resource_state": 1}, "name": "My Giro d\u2018Italia tappa 12: L\u2018Aquila - Casteluccio di Norcia", "distance": 125278.0, "moving_time": 18613, "elapsed_time": 21318, "total_elevation_gain": 2451.0, "type": "Ride", "sport_type": "Ride", "workout_type": 10, "id": 11533061977, "start_date": "2024-05-30T07:38:47Z", "start_date_local": "2024-05-30T09:38:47Z", "timezone": "(GMT+01:00) Europe/Rome", "utc_offset": 7200.0, "location_city": null, "location_state": null, "location_country": "Germany", "achievement_count": 0, "kudos_count": 9, "comment_count": 0, "athlete_count": 1, "photo_count": 0, "map": {"id": "a11533061977", "summary_polyline": "agoaGcxwpA|D{PiLmMeC}RtVue@fAk`@_DgTa]kw@ek@xDhBoIsNmF~DiHmNi`@`IySqFsC`T_TfFmU}Mol@rK_p@~Se`@}p@a_Asl@gB_o@gt@anAmz@i`Bw[eTm_@kEzMyx@gNob@pc@mRpa@uJjh@w`@bvAi@no@uK`PBhPbChYpMsA_D`J`LtJmR|X|MtBkDxQeNfM`G`QuI|EkAbMwKqFaDpSsEvIoLfKVjKyHbHQbJuQr@{EdKjHpDkAzP`IbMjLtEi@jf@_NlZfJjI`K~PqLpP`Ixb@mDpN`HxS_CnNuGrDj@tb@_ZhQyOno@nJ`a@gD|OhExJkDrFrImDi@xDwSl[}B{GcAhU}EuQ|@oN{y@tZ}cAm`AgH`S}DgQgJiDeHzDi@nXsGs@oFnMgP{JmTqGP~NeGxEjBhGcL~I{DdPkk@mj@uFkPqPjAwX_}@oZrLsI_[}JnIcEiEg^lXyNg@wCuU{LbDMaU}PoSeQ~n@Rj[iNbMf@tN_G_@u@vIoIkFkAhZaMhJdB`O_Qz]q@fc@sM~B_FrSxAmDiCvTcMvDiJjZ_]d`@aPhg@cKhLeHlqA}K|[tUzk@{NjMeG~UkLvHX|P}GxDlJWvEtBeGdE~IvDtAmKn@~M{G`CwAdTpOlPl`@zCPjLdJvFjEcCgFkM|J|Pp[_GhC|RmZ`j@mf@oQ_OfCwm@tl@ch@zS}c@oc@g[sNyl@}JcDfJ{N}TM`S{c@bCbAqI_HeDUcHkLtESoR_IqEbAuQsF}B|CsM~IkAyCuFlG{NcQ}@aDxIoFkP_KfCvAyKqBq_@tCj@gB{VnGgEaHmL~KuB`PfJc@gKoNsJdAcLgS~KgO_@gCy[aD`QaRFiIlL_DlVtOjAi\\}@gDlScNvNsfAh_@qKfSqm@tEkZl[aChNiw@dLaBuKjD_NeLdDwg@}Qg`@dEuq@x_@a\\`w@{R|H}|Aeg@mdAej@qVwWaq@v[qf@yLgf@}b@ua@yx@y_A}l@ua@sz@uRc~@bApX`H~SoHlJz@nSgJlQqAuK}MaDqc@v@zAuHcAyDiq@eYuHhBwDhLmEwKcH|KcGuEGrVqNaSn@jt@eBkJm\\gKcGqMhAmIoDbFE`]j]xb@`Bj_@bIpDlW_M{HtF}@bM|Ubi@wToMdF`p@fQ`]v^|KrCpPw`@rf@kIrZma@p_@kKeEq@rTsPrAceAfy@mNniBqs@yGrJhe@{H~Rx@{E", "resource_state": 2}, "trainer": false, "commute": false, "manual": false, "private": false, "visibility": "everyone", "flagged": false, "gear_id": null, "start_latlng": [42.35, 13.4], "end_latlng": [42.83, 13.21], "average_speed": 6.731, "max_speed": 17.582, "average_temp": 20, "has_heartrate": true, "average_heartrate": 72.0, "max_heartrate": 72.0, "heartrate_opt_out": false, "display_hide_heartrate_option": true, "elev_high": 1542.2, "elev_low": 605.6, "upload_id": 12310987573, "upload_id_str": "12310987573", "external_id": "garmin_ping_344207622652", "from_accepted_tag": false, "pr_count": 0, "total_photo_count": 6, "has_kudoed": false}, {"resource_state": 2, "athlete": {"id": 4495383, "resource_state": 1}, "name": "My Giro d\u2018Italia tappa 11b: Gran Sasso trailrun", "distance": 7621.5, "moving_time": 3961, "elapsed_time": 4395, "total_elevation_gain": 500.0, "type": "Run", "sport_type": "TrailRun", "workout_type": 0, "id": 11519717198, "start_date": "2024-05-28T10:33:25Z", "start_date_local": "2024-05-28T12:33:25Z", "timezone": "(GMT+01:00) Europe/Rome", "utc_offset": 7200.0, "location_city": null, "location_state": null, "location_country": "Germany", "achievement_count": 0, "kudos_count": 10, "comment_count": 0, "athlete_count": 1, "photo_count": 0, "map": {"id": "a11519717198", "summary_polyline": "g{`bG{tvqA[|@y@|Ak@n@MP@RN|@HzBLl@LhAAlAGlADHXPf@j@`@RNLdAzA\\p@t@fAN^HTFXBr@?jBKl@O~AO`AGNo@t@eA|Ai@f@WLSTOpAIPBlAAx@CT@VH^Ar@XlANJRTJ\\Lt@BTInBIPIFg@N[@o@RaAh@a@Ny@h@mAj@K@m@^a@Fe@Rw@Fu@Lg@X[Jc@VMLKRSl@e@v@Up@Mf@UpBKdA]nAIACMOK?EKCQMK@GEEBIVKJCEAi@Qa@U[EGi@Yk@Sy@Gm@@QCO@GHy@HUL}@NyA@k@Y[MQM_@m@Ka@KUUUE?w@_AOEi@e@KQSCKBs@K[?YEACAk@KWIIGCU?g@cAGGEOEYGoAAoAF_@A{@EKHiANk@YUEUKKU?MCYOo@Zq@HSHc@I[AOG][MJo@P[B[HICCEEa@_@cAE_@Eq@G[MG{@h@UA]UM]ImBG[YOS?QESAEGEQKs@QWSAII]CGIMGCEYB]GYWm@UQe@w@]KKW_AGs@Kc@GO?u@Hq@CUAEq@HQEUa@CWBc@HWLaAVk@BYLU`@qAG]DcAKoA@[Ig@Do@Gs@I[@o@CY?OCYg@kAAc@D_@Vk@|@sAd@iAT_@Jy@RKH?@B\\[FUXo@XWHSTOBIDa@F_@O{@KWAIF[@_@DQCKOGM]AGTURYzAcB`@]h@[v@Gn@D`A?ZF`Ad@N@LC^@LHHPHAHGtBEDA@CDFRLr@t@XRVJj@d@l@bARp@`@x@RR`@Pb@DPLf@r@PN`@DnA[r@Ch@I`@ANJb@Hd@X\\LLRVRh@NF??IBEHFJBDJHF@Ld@fA@HVNhAtE`@dAVj@Pj@d@dADL?VJV@NJ\\PVBAFHR\\NPh@TH?\\Rh@f@NTLh@b@fAHDB?@CGs@@IJ@JJZf@DKM}AHC?EEYBm@Go@Ko@?GH@JHB?Ee@BE\\\\@CCw@LPDIF?Ga@Ok@@ANHl@v@D@Ko@YeA@GDAFBTRBAIg@M]@GFABCEK@CLEHBAIBEB?^ZOeA@CR@NLpArBTVHsDZ_DJk@H?`@\\DQ@[DC`@DBKFqAFCJ@j@PFAZSFKLMDWFKZMVQx@Gj@Lx@a@bAa@N@NFT?dA_@f@[`@AZUF@", "resource_state": 2}, "trainer": false, "commute": false, "manual": false, "private": false, "visibility": "everyone", "flagged": false, "gear_id": null, "start_latlng": [42.44, 13.56], "end_latlng": [42.44, 13.56], "average_speed": 1.924, "max_speed": 4.246, "average_cadence": 73.5, "average_temp": 19, "has_heartrate": true, "average_heartrate": 132.7, "max_heartrate": 154.0, "heartrate_opt_out": false, "display_hide_heartrate_option": true, "elev_high": 2404.0, "elev_low": 2076.0, "upload_id": 12297254153, "upload_id_str": "12297254153", "external_id": "garmin_ping_343792039047", "from_accepted_tag": false, "pr_count": 0, "total_photo_count": 4, "has_kudoed": false}, {"resource_state": 2, "athlete": {"id": 4495383, "resource_state": 1}, "name": "My Giro d\u2018Italia tappa 11: Castel del Monte - L\u2019Aquila", "distance": 76354.4, "moving_time": 11467, "elapsed_time": 30110, "total_elevation_gain": 1325.0, "type": "Ride", "sport_type": "Ride", "workout_type": 10, "id": 11679053851, "start_date": "2024-05-28T07:39:20Z", "start_date_local": "2024-05-28T09:39:20Z", "timezone": "(GMT+01:00) Europe/Rome", "utc_offset": 7200.0, "location_city": null, "location_state": null, "location_country": "Germany", "achievement_count": 0, "kudos_count": 0, "comment_count": 0, "athlete_count": 1, "photo_count": 0, "map": {"id": "a11679053851", "summary_polyline": "ouqaGqcwrAcEfBxAlLm@xNIqKoC}CiCqRzF}EjDeKB_PwAeGaDy@uB_DiDk@iQ|CaSbQuB_@`Asq@cIuA}CxGgAw@p@}CzMgSvGi\\{BaAoMrBkGyAqAyH~BqDcCaEk@wG{K}DPiDsAeF~AgC_@aEn@_DcAaCt@uMoAcFr@sC}AkGmCeBiNhCrJ|@d@tLsE|EkSbk@}BgAkK_U_GZoFtC{GiCMgBbEyKKwDaG~CyFmAoNdAiPdYh@|X_CdPwO`HkS{C|EzFh@dMpDdG}EhHaKf^SvDdX`kAzB~ZoE`Ku@pF`JpGt@tIqAtEBnIbIzZzDh^cCr]pAni@nQzg@mC|_@eBhoAaFbZhCrq@iAzLiSjj@e]rp@kL`MiEvJkAfI}Ac@uMmXqSnCsc@pNgPnKmj@vh@sQrn@uErl@qAxc@_GrTgBdNeJbRqI~HdInLoD~AoBjGnB`LbBxYuCxLq@ba@iVxJaFaDVhF`I`I_F|HzC`Gc@pB_Ab@{DeD~D~JjL}F~@jIvF|AjArDUo~@XsZ`@cInC{JwEsf@vBoGjDeAgIaMvIyHfJwRdJod@jAsb@xEyl@fQsm@`k@oi@bOyJje@gOhOuC|CpAhNn[aDdTqFjRcAfi@pAbExHzDzMmDhBnBHhIuGzhAtDxg@mAtI|ClQxFdP|GvE|Ak@RcIvBiDfVcMxFtIrI|Dv@nKrChKbFzHsEjGOpLj@|UhDjUnJbEpNuB|E|C{BxOaG~IgBtGcGx@tDfCvHqFeElHrCFUrAuJ~BiE{AwN_N{IfAtFlEbFnQHvCeCvKr@hF`BnB`DH~DgBbFqG|Hi@dGxApJkC`MaSfCpKkB~q@dAxM{@hEfEmAJ}FbFjAdGgEfIbWzLhKjFbRfKoBcBxE`BxHtJuEq@hHfH~PzLxDsBvFsAhN~KUgOfHgHHwFjJq@zE{FtE{CxGvG`Cr@`DaBlBhE|@bFxE~C`FpAfGmF~CwBdGuDbBqC~FUrJqCnB_B~`@uDdPwF|HkAIq@qPj@yGmBcCMkH}@c@yBdS}AtDFvD_DdD{@`LuBbFrAtEkDaDh@uHmE_EeBrFh@hIy@`HeFl@mBxFt\\bPlKlN~KzF|OdXdK|GdWkAjOnA~JvIhP|[vEdE|FjK_@|DwDpIeFjEiE|KeGpItBtHdCbB[fH{EdUxEnK`Gb\\{DzJq@`JoFnI{EJiEfI`@bCxCg@h@fAqEhH{AzJfEvCRvDnBnC@hFvChI]fBeDxABhBvNjF{A`Jvb@eBtFgBn[ht@vAxPpBbDQxHmCfJ~ApLsW~g@vCbPlDhFJrBbGxBq@dD", "resource_state": 2}, "trainer": false, "commute": false, "manual": false, "private": false, "visibility": "everyone", "flagged": false, "gear_id": null, "start_latlng": [42.37, 13.73], "end_latlng": [42.35, 13.4], "average_speed": 6.659, "max_speed": 16.744, "average_temp": 14, "has_heartrate": true, "average_heartrate": 78.3, "max_heartrate": 92.0, "heartrate_opt_out": false, "display_hide_heartrate_option": true, "elev_high": 2132.4, "elev_low": 630.4, "upload_id": 12461281267, "upload_id_str": "12461281267", "external_id": "fitfiletools (11).fit", "from_accepted_tag": false, "pr_count": 0, "total_photo_count": 6, "has_kudoed": false}, {"resource_state": 2, "athlete": {"id": 4495383, "resource_state": 1}, "name": "My Giro d\u2019Italia tappa 10: Castel San Vicenzo (Belvedere) - Castel del Monte", "distance": 140252.0, "moving_time": 21324, "elapsed_time": 26078, "total_elevation_gain": 2546.0, "type": "Ride", "sport_type": "Ride", "workout_type": 10, "id": 11509966709, "start_date": "2024-05-27T08:26:53Z", "start_date_local": "2024-05-27T10:26:53Z", "timezone": "(GMT+01:00) Europe/Rome", "utc_offset": 7200.0, "location_city": null, "location_state": null, "location_country": "Germany", "achievement_count": 0, "kudos_count": 8, "comment_count": 0, "athlete_count": 1, "photo_count": 0, "map": {"id": "a11509966709", "summary_polyline": "_~b}FsgwtAdS~J}h@uEaJsGo\\f[eMxBqBhK}Rwd@oGoBnBkWiNaNiDrFq@q[uTnk@uAmN_Hb\\oMvEiXbq@{YzXyd@|Hi`@ha@fF_SOwbA}Rfu@}MxS{TdIb^ok@pJ_b@u@sPIfPkNz[_J~DiF~QsQfJ{J{K}ItVqVfGiS~TeJo@oJwKqn@gDoPgSkKhE{OgN}GvCwl@a{@kGoXyCqh@TeLsGpi@rE`lA~F~NuB|CmPuMca@clA{`@esByUdEpGGo@_LyNcPaUo~@s`@_\\rEeS}PYyI_N}k@}^{j@iSoI~Bc@{Tc_@uNdEuEeBq@{PzG}lA`@ce@cOkJ^aCqIyMhHiQaFcl@`f@e^vFoHsH_BrFkNRgJpZsZpa@uYtDmOzWe{@nl@cC|If@lg@mM|]_ObRgj@_w@yD@gDwSqmAqFy]nVuTrd@oSkAeEve@kIbJuy@dZkZsNik@Csi@r{@}kCd~AzBnOzUxFkMrRkj@wJiw@`W_K}GiSL_{ArfAfn@gMqLjBua@v`@yGg@aN|Qim@dWcE[kDcKuP~LfC}L{DmGgMhFgAcJtE}[~JrDcMmX}MnJoVfBzFlBwHzGYvIdIcAyK~EwSqVnHmSwJxNEdJ_LmAyW|]}Q|Cm_@lWwEnKyBd\\edAdcAmJ}IaRtAgGfV_NxGyLfa@t[pm@gHjYeExu@sWtyAy]uJq]jc@cQpGmDjKfAtHo_@pl@gd@vlAc`BbmAfC\\wHgPwAc^jJoG_RmLkf@fZwTxA{JbIqHfd@qSxg@qv@`b@q@dQkWhOkg@~k@{a@faA_WnS{_@zIe[`Ysx@znAgu@e@eQbS}AxYqDrEwb@jIyO}I|@yWeIcOk]aHei@s\\uKoV}_@bb@mGx[cg@fI}O|t@cL`T_v@th@m_@ZeUhLy{@fI_aAqE{j@db@{hAzf@ay@rbBsZ`cB_i@vw@sBqA}h@ll@yLmAnF|OqHzUyBvh@_OjEuIhL}Ins@gPmY~GnU}DrMf@{KgVoKoHHfQhQaWyHlIxDo@|VqF}Qk@r\\uEeV`BhPkBrFaCgMCpOfB~MjLtJrA~NsQfTuSoA`K|e@aBlOsRbe@fH{n@yL`d@{Qt\\}Kq@gSeX_CtChB~KqBoLxBwDoNeMa@_y@oQnMmN{AqUdHgOsD_MrNeM{XmGlAuNeR}SbHeQoKmHfCgTww@t@|v@{H_f@c@rFuFqGuCcP{KkJn@wD_FjLdCwG", "resource_state": 2}, "trainer": false, "commute": false, "manual": false, "private": false, "visibility": "everyone", "flagged": false, "gear_id": null, "start_latlng": [41.64, 14.05], "end_latlng": [42.37, 13.73], "average_speed": 6.577, "max_speed": 16.875, "average_temp": 22, "has_heartrate": true, "average_heartrate": 125.6, "max_heartrate": 159.0, "heartrate_opt_out": false, "display_hide_heartrate_option": true, "elev_high": 1348.2, "elev_low": 246.6, "upload_id": 12287208948, "upload_id_str": "12287208948", "external_id": "garmin_ping_343505172386", "from_accepted_tag": false, "pr_count": 0, "total_photo_count": 6, "has_kudoed": false}, {"resource_state": 2, "athlete": {"id": 4495383, "resource_state": 1}, "name": "My Giro d\u2019Italia tappa 09b: Napoli - Castel San Vicenzo (Belvedere)", "distance": 139505.0, "moving_time": 19117, "elapsed_time": 24989, "total_elevation_gain": 1661.0, "type": "Ride", "sport_type": "Ride", "workout_type": 10, "id": 11504482346, "start_date": "2024-05-26T11:02:50Z", "start_date_local": "2024-05-26T13:02:50Z", "timezone": "(GMT+01:00) Europe/Rome", "utc_offset": 7200.0, "location_city": null, "location_state": null, "location_country": "Germany", "achievement_count": 0, "kudos_count": 11, "comment_count": 0, "athlete_count": 1, "photo_count": 0, "map": {"id": "a11504482346", "summary_polyline": "e}uwFephwAe[_Kma@}Zm]_N{SySmSyFwVsg@}FvA_h@~\\qRzWkYiYwj@sIuYxJco@oOuLaHkZOoYoCas@iL}}@bKsc@yG{_@zYyOlg@ob@rG{W~PeRdVcGpZ{MxvA}Qju@}B_AKiL}gGas@o}@kTkDjR{i@eJwj@dE}e@ji@yU`^}nAj]iiA~{A_a@jvBkPzUi~B~e@qx@nLs_@qEqdAO_Mom@sJsEco@vFek@`Oo{@qOea@gc@sm@i}@oh@_TkMqNuOuXwImd@m]yZit@}Mu\\bBeOuPgQmIuCiHoDbSaYsPVtD}U`j@_JtG}Tl]gBdOqWvM_NrNcEbTvAhOqBpM{Px^iNjKmNt^kL`QyIfFcApFg^aSmKqZqMtVg]rYmr@vlB_Bfq@iUn@iNlNRoTgAhH_KvIlFoKePfOeJGeLfRiD`Lf@yPkJzVwElEoK|@gN}I{Ke@{`@tSwUwTmq@kJcNoJsTiE{i@bG_[p`@aJdRkR|BeQ`QkThd@sQzIiA|NsCnFe^n\\}Qi@aWvXcJxSoTfA}WzKo\\hX{Q~a@@jO{BrGqTpNsW~^aH~ZeE|DBjP{FdSgK`Iqh@vMoCpDcBjw@aInRvDxNeh@lu@aZ|f@eDv^aNtJkX|h@{`@na@ab@j\\wOxG}Lb`@XpKkCzKqp@xMoO~b@{X~e@ma@``@uY`DoNkY{MgJ_C}SiQg_@oBgNup@|`Bgi@jhAk\\|S{KhB{XhAaZePcc@rt@mItWeMp@iCbIgQ~MMbHkWsGaGoRsNwK}Sgr@sIkJ}b@{GeIfFcGgN{RoCgEiFaBwDr@sKuB}EuRrCeDtJqDIeD~OmLrM_G|Zw|BtfDoZv_A}SxGuAlE}FrBcBdIkJfBeH~OgKdHiCfIg_AhsAoa@lX_x@|HwSuYmKyBwQ?cCiIa@{YyKse@z@cNqCqSoP}BwJfF?j\\w_@cIwUl`A{nA{LmdBlz@wX~GoJ~HaLtXiFiBj@kSaCqDkMpA_KmKkMwBeEfIqMhEoGzJwIqE\\mZmN{I{RlByKfK_DlLeb@dO_N`N{NdYcAjMsJtZ_I]iFpTy_@zFwHmCqOjBmJpKrNxQxBrPhIsF~GhCqB|LtEzCj@lEeFfFYjLoJ`FkS~^{DzA{GnRZ~F{D`Oz@jIeF`M|B`b@cIgR{CW}D~G~DuA`@xK}Cu@{ObQuKhDkCxFyHoEiOnCy@bJeClC|@lZxMfOyA|QuYid@oa@bJcOoEcEoJ", "resource_state": 2}, "trainer": false, "commute": false, "manual": false, "private": false, "visibility": "everyone", "flagged": false, "gear_id": null, "start_latlng": [40.75, 14.47], "end_latlng": [41.64, 14.05], "average_speed": 7.297, "max_speed": 16.8, "average_temp": 24, "has_heartrate": true, "average_heartrate": 130.3, "max_heartrate": 163.0, "heartrate_opt_out": false, "display_hide_heartrate_option": true, "elev_high": 737.6, "elev_low": 5.6, "upload_id": 12281520470, "upload_id_str": "12281520470", "external_id": "garmin_ping_343304425208", "from_accepted_tag": false, "pr_count": 0, "total_photo_count": 3, "has_kudoed": false}, {"resource_state": 2, "athlete": {"id": 4495383, "resource_state": 1}, "name": "My Giro d\u2019Italia tappa 09a: Vesuv", "distance": 14565.7, "moving_time": 6398, "elapsed_time": 6597, "total_elevation_gain": 1162.0, "type": "Run", "sport_type": "TrailRun", "workout_type": 0, "id": 11500771605, "start_date": "2024-05-26T06:12:00Z", "start_date_local": "2024-05-26T08:12:00Z", "timezone": "(GMT+01:00) Europe/Rome", "utc_offset": 7200.0, "location_city": null, "location_state": null, "location_country": "Germany", "achievement_count": 2, "kudos_count": 2, "comment_count": 0, "athlete_count": 1, "photo_count": 0, "map": {"id": "a11500771605", "summary_polyline": "c}uwFaohwA@JOp@B`@gAfB{A|A_@NeApAo@p@o@^}AvB_@H_AbAc@Nq@bAgAlASd@y@v@[n@mAn@y@fAiA|@gApAu@b@sBrBg@RUXg@TiDl@ML]z@Ev@Df@Mj@[`A]XKVCVBt@Gj@EBWJUQ}@M[Sc@Cs@aAUM]IaADkAo@[Gi@No@bAgAl@[Dw@Wy@iAc@KPp@EXDjAY`Da@pBKNy@McDwAgAYkEiBiA[c@_@cBo@w@s@[MSDa@lAOvAs@xAyCz@[X@bAy@xJOhEOpBGVIFgBk@mMqBIIAKH}AASC?y@HwB~@}@t@g@T{BzAiBjAeFnC}@~@sAdBs@\\}AT}HZwCIeC_@uAVk@a@u@C_@FeAf@gEvEeAx@MZIvAy@~ByChCu@pA_AfAmCdA{BjCmCdBaA^qDfC[LkAFgDUcBHoBj@mB^{ClDmBtAwAtAaHB_ATKJc@BoBv@{B`@wAOyFLYHSd@DXIf@BJA{AGHLj@i@~@APF|AGjAUrBS~@QTqA_A]g@o@qAg@g@YLER?TPx@JhA@l@KZkAi@cAEkBHMLAJBtAONi@HQKMaAUy@g@gA]YqBaAsA{COOUBKZI`CBNXb@Jl@Dz@CTIJQG_BcBQWSg@]g@gA_Aa@OKFCPBrAY`DYbBgA~CG`@FdBCZQVM@KEe@oAiAuBi@yAkCeD}@aCWWoB{@m@iAY]G?J`AJzBv@pC?TQlB@d@TtBDtDV~ACzAGRGDKEc@cAs@uBoAu@M_@{AkFq@}EcA}FOa@oAmBq@oBcAwA{@e@{Bm@sCkCcDoDg@YUD`@jAr@~E^bAj@lDSzBm@dCc@rAG~@D~Bc@|BOvAMTWA]QkAmASqAQm@_@s@o@i@Su@OMs@Qa@WiAVs@FaAfBq@l@u@FSKY_@c@IeATeBfAk@Ge@Wq@eAYE}@Ls@UUOc@g@KJPd@vAjA`@f@\\r@T|@`@tCzChEhAl@r@rAERO@o@c@}@Ek@SaDeBy@}@k@iAWQYEqCH{AyAgAOm@SaADu@TmBXc@Ry@|@]Py@LKJAPFH^DhAYj@[t@GxBrAzBfAV\\hCzBZ^GLeAa@gCc@mABk@RX?ZXW\\w@\\g@JON~Ez@fAvArC`CtAjCDl@CXMV`@bA|@xEGfA?tB_@`BDpC", "resource_state": 2}, "trainer": false, "commute": false, "manual": false, "private": false, "visibility": "everyone", "flagged": false, "gear_id": null, "start_latlng": [40.75, 14.47], "end_latlng": [40.82, 14.43], "average_speed": 2.277, "max_speed": 5.24, "average_cadence": 79.0, "average_temp": 27, "has_heartrate": true, "average_heartrate": 144.9, "max_heartrate": 165.0, "heartrate_opt_out": false, "display_hide_heartrate_option": true, "elev_high": 1168.6, "elev_low": 6.2, "upload_id": 12277698961, "upload_id_str": "12277698961", "external_id": "garmin_ping_343222080802", "from_accepted_tag": false, "pr_count": 0, "total_photo_count": 5, "has_kudoed": false}, {"resource_state": 2, "athlete": {"id": 4495383, "resource_state": 1}, "name": "My Giro d\u2019Italia tappa 08: Cetara - Napoli", "distance": 91665.2, "moving_time": 13831, "elapsed_time": 18415, "total_elevation_gain": 1420.0, "type": "Ride", "sport_type": "Ride", "workout_type": 10, "id": 11486817077, "start_date": "2024-05-24T09:13:33Z", "start_date_local": "2024-05-24T11:13:33Z", "timezone": "(GMT+01:00) Europe/Rome", "utc_offset": 7200.0, "location_city": null, "location_state": null, "location_country": "Germany", "achievement_count": 0, "kudos_count": 9, "comment_count": 0, "athlete_count": 1, "photo_count": 0, "map": {"id": "a11486817077", "summary_polyline": "skbwF{avxAtRgBfCiDrKrUhJlBdI_AqClI~KL~ApDuO|b@j@~DpUmJxDiIfErAlGxSmFhZ~AdMZ`L_LnCgAjZ{FhBEfHaCXNjSgKvFiEoB]dFrCdFzE@KtIuFOeIzRhCjBiC|DxCdLaCdG~@|PuBlI_Nk@p@hJlHtEiE|JaKjGj@vDcL`a@_CxT`@xHpGtB}ApQsFhHj@rP{HnDjNs@hE~U~DpBjAbOxOjFpFwA`AxHdIfGrDpKrKrE~A~IhFf@HvHhOvI}DvNhCle@tFrM~J|HfSv[bH|UuHjMjNb@pMnUdGfCpSfYlRm@fBjIkF|AkEzQ|BzPpC`C_GlJvFnRmBvJtJf]wEbl@SlOfBzCaClGlDxDpAxLgGnEtRtGpHh]lL`QuBrPmV`WcMjCwC{EgF~@fBvMsNbBhCxRoClAr@xDkFdBp@dEyJpSuFvEyHrAaHu@YxFdI~CnAzUyE`AlBvJqMlYcJfBpCzDaDnHnBvDuBpGbCtFcHbPuMpGlBhE{SrDjB|H`Lj@vAvHjJyB{Ch]bNuIhItF~AtUlCzKjCzE~G?jDlGCtW~KsB\\lLxFbGgB~K}NtQzBvGmFjUxCAxH|RxJrh@QxMxF`NS`HvGnAgD`K|FpG_IuDkAaG|CfPZjLwHlNAfXkDnRjQdGwCxLtGtj@hCrJ|P|ByDxCvAxGxEBbDcC_MfP_DjPpMpFfFvKLxM}CzYgJ`W|IqDdC~BUpMl@jNhIdUzDz[bK`@vB`OfG`@vJlNdRfd@eDiDBfIvHQxAeDcBwE|GdKtA~WQlOxChDe@vg@tCdHnHElCpb@lHdCaBxQsC_Ax@`FpE_@nB~DkLh@rGxEpDlYX{LvAE@hQoGgA}GcQ_S`KcNGvC}LqJzFaDqFw@pCaP|BmY]y@qBvMm\\mDcD[qQoMmK\\}EoCyEyOQkDvLgG_GkJlE_Lg]oKnNyUtE{IkFrEeWgB{BjAqJsKfD}@iQ_H`A{H_KtIwDFmN~EqC_MkMbGoMhOmH~BqGyZ}gAuDqa@iHqHuLs`@cLFcDgKfBeHj_@}^uCek@bHyKfBaLuC_MuVg\\gHfFuK_P}GvDgKgAwPxJ_VtY}VlL_VbZaJb@iEsEg@k`@xBeI}BmLdJeZaBaSwEhIsBcK|CgAjEuO}A_JiInI_JXyAtPsItGaCeDnBgDuC{FtAoByFiIv@eKsHDuGmHoUsIaKgNyW}BmTkEuLoH}e@obAyFmp@wH}H^yJvHoQc@gr@bDyIn@_^~BmBvAm_@gJ{Ma@iQcNlOgKbHwJeLMwJdCoG}AaCkF|IuLtKgIwGyQ`AWvFcV{B|Glb@kgCb{@iCcNua@|SwJLwUuWgj@uI{Q`HuDh~@", "resource_state": 2}, "trainer": false, "commute": false, "manual": false, "private": false, "visibility": "everyone", "flagged": false, "gear_id": null, "start_latlng": [40.65, 14.7], "end_latlng": [40.75, 14.47], "average_speed": 6.628, "max_speed": 14.522, "average_temp": 24, "has_heartrate": true, "average_heartrate": 124.2, "max_heartrate": 168.0, "heartrate_opt_out": false, "display_hide_heartrate_option": true, "elev_high": 469.2, "elev_low": 4.2, "upload_id": 12263274935, "upload_id_str": "12263274935", "external_id": "garmin_ping_342804516962", "from_accepted_tag": false, "pr_count": 0, "total_photo_count": 6, "has_kudoed": false}, {"resource_state": 2, "athlete": {"id": 4495383, "resource_state": 1}, "name": "My Giro d\u2019Italia tappa 07: Marina di Camerota - Cetara", "distance": 129763.0, "moving_time": 18455, "elapsed_time": 22941, "total_elevation_gain": 1261.0, "type": "Ride", "sport_type": "Ride", "workout_type": 10, "id": 11480604589, "start_date": "2024-05-23T11:09:20Z", "start_date_local": "2024-05-23T13:09:20Z", "timezone": "(GMT+01:00) Europe/Rome", "utc_offset": 7200.0, "location_city": null, "location_state": null, "location_country": "Germany", "achievement_count": 0, "kudos_count": 10, "comment_count": 0, "athlete_count": 1, "photo_count": 0, "map": {"id": "a11480604589", "summary_polyline": "q{csFwcy|A{B_CyBrIjBnHsApMrBdZxEhUeHlLyTaCq@lJ_FdGsDpOlBlLxMdVVpJaZza@oMnLmw@r^gJjMqJjA}ThS}[pi@}c@hR[td@dFp\\c@pFaf@|SiLfJcBpF`F|`@lQZfB~Dgy@tc@cw@pOwu@t_@gMfBgCpIaJ?aN~KmL~AF`FcHxEyMdC{Rx]yG|a@aR`HwBrWwItUiAhMcErCmAdGkQbTaPtMqC_@eB}HoCpOcL`IuWmG{FjNp@vGyLhDjNzUwPvLCzHgL_AgKrVaFHoXxZsFzL}InJcDB_Mtj@Et}@gJe@_EcHsQkD|@{KgL|JbA`DkElKjLX~IhNxU|KqYxBxH`IqGhLwg@gGU`EqYjVgBlGiP`GgHfRaEiDz@lHsEiJMoNoEh@uE{LsMeFdH~JwGhWCvS`Idq@fG~IuSzOsLzPiN|a@}AdO_IIoNiMoPcB{NoLwM|Bam@yBeRi\\}F~InBlNwJh@wLl^cM`Jak@e^yL}Ryf@pAoZiMi_@qEwO`ByTiJ_]o\\oEhVgOvSaJjCgSdTeGjKiBnNmZr]mQxZwTbPygA~f@iAj]}J`KwL|Bm_@qG{IrDkHeAgGjFyDUcElO{HfD{Sx@{XnKwN{A}RnKuAwBrAmIuFwCoSe@{GhE`HuApPhGeAfb@iGlKNzHsJhG~E}MlAwLsAcSsAqAyBdK{OdMmIr^b@hHcEhOg@vPoD`EX|JaJlMSvm@rFpZq@xGjGrVQpIsCxH@xPgNp_@{KhMcWyB_Ym@wElGmCzNig@nJeK{BmIsMm`@yP`KHsM{EgeAnR}RfUuDbTiIl@}HrIcD`P_JjM^bGwBoIpBhHiDzPtCnSsPhLqCxOrApJrMhMoAnNo\\aSke@f@aQhRiZYoGjJj@rReGsMfByFkC}PmFkB[fJrC|@uDk@wC_YyDkB{@`C~DjNqClIr@pGqK`LdAdJyM{Fms@nEms@tb@_JxQyOAwdBrdAsh@fCgOrFx@vh@ij@xe@oBln@clAld@mfBd|@~Hlb@}@fGc`BljA_f@hFyPdUooIlvDsvFv}DoRkC}DlEoDdS}uCfrC}|AxcByMnCqFbGwK}C_X~c@vEfLuz@dz@ai@~q@gRpXs`@vt@aCYqLxRgUtQw\\~q@qSbi@mk@f}CkBj\\zE`YfAde@lLxX~WdQzBbNgCpM{HxEkCzOt@hDjO[lBzHmCvIpEiApFdFrAhIxVjOsCxWrMuGzC`CdAlHnCqBfRfFDtDvK~KdLdBxM`KlExIhLlCnGg@{@~RyK_@}F`KbEwC", "resource_state": 2}, "trainer": false, "commute": false, "manual": false, "private": false, "visibility": "everyone", "flagged": false, "gear_id": null, "start_latlng": [40.0, 15.37], "end_latlng": [40.65, 14.7], "average_speed": 7.031, "max_speed": 16.775, "average_temp": 26, "has_heartrate": true, "average_heartrate": 124.5, "max_heartrate": 156.0, "heartrate_opt_out": false, "display_hide_heartrate_option": true, "elev_high": 414.6, "elev_low": 3.4, "upload_id": 12256875483, "upload_id_str": "12256875483", "external_id": "garmin_ping_342594221846", "from_accepted_tag": false, "pr_count": 0, "total_photo_count": 6, "has_kudoed": false}, {"resource_state": 2, "athlete": {"id": 4495383, "resource_state": 1}, "name": "My Giro d\u2019Italia tappa 06: Amantea - Marina di Camerota", "distance": 185763.0, "moving_time": 25157, "elapsed_time": 29675, "total_elevation_gain": 2079.0, "type": "Ride", "sport_type": "Ride", "workout_type": 10, "id": 11472038267, "start_date": "2024-05-22T07:02:43Z", "start_date_local": "2024-05-22T09:02:43Z", "timezone": "(GMT+01:00) Europe/Rome", "utc_offset": 7200.0, "location_city": null, "location_state": null, "location_country": "Germany", "achievement_count": 0, "kudos_count": 10, "comment_count": 0, "athlete_count": 1, "photo_count": 0, "map": {"id": "a11472038267", "summary_polyline": "}jtmFencaBm]xGwHoNmB~H_mAfa@ig@rM_[yAgrA|`@{mD|@igD`T{pEjN_k@qPmRm@se@|Og_Br@}pA~Nqx@mB_yAf^ytAcBm\\lJmUvRk}A`WcsA_Igu@lEg^zUob@~p@mTnHs[pRa]dg@{cBhp@iaAL{w@xq@ylCbaAk[rb@w\\dMebAhu@ceAldBwrDxiBqb@nHoh@fz@udAxt@i^`~@_N`NmNni@}DzaAeZbf@}Oxe@_o@zPkQvPy_Cpq@qx@iBk`@~NgWfYqlBjUou@jPs]``@}Wbn@}kApXgm@fAi^|Uog@Z_g@hTk`@xWmV|_@uCyAfApR}FlXq_AvAcq@vV_jCbBqfCbVadG~pAgqDt`@ad@bQks@bw@iMcHiQc}@eL}Oqr@{Yar@yKcZfPy\\uNcMKpApEcLhIaSk@pHhFoNgA}ChUiO`DiEbLex@Wqk@pKqBfMq[jEi^|Wg]pF}eA|x@e^iF_a@oX_MnE~BU_QbOc@pHsc@mB{VjPhSrHgPrPl@dWwAwe@jGiIs]aG{Q}Nci@uEcZhHiYkOwa@uf@oOaw@qMaf@qdAwc@ePo^eTVeM`Y}LlFmW{Di[hSsZkKay@rNq^iSeL{g@{SqL{^pVgVKgEhPyNdNyE`~@}Sh`@{x@nfAw[tJcV`XqJdYw@rToZrh@wc@hJou@fdAa\\nKsMpb@viAhp@l\\|l@`MnpAxIpDnK}JhHdW`OrKmHl_@lUKrClWaBvNqGkV_a@pXo@nKfKgMdMt@wHhd@dPwAd@lJ{DpXqKlSk\\hNpGpHpXuBdBlU_J`c@lKzLgT`[qRmBtIpI}ArT{DiG~BgOwRzCiFkMgDnKqObFeEuI|BfL`LtHzLqB`CdM{FyE_A`HrNr]vC~n@aWn\\{F~XdClOvOpGxKhTeZzw@wHfe@iAtv@i[f^cEpo@rDnb@|Wl_AkAzoAhPniFlVfu@cIjKl_@RdOzK|[hCnRxf@mCtGbKtHoK{AbCdEoQ`JsRb[~PnIbA|H}Gs@eIvKmJxe@_OfNtOeAW|VtFnQ`MbHlFsJ`AjOpLtRPb_@dShQvAvIfS_M{JlYhEnUeFf^|Zfn@f@zLn\\lUfe@taAbUqJpS|RzGmLzKxSdE`s@|F|JiG|LfFhn@dMbo@q@r[jMqj@fM~NhFkFlBdL~EwAzJbRpEyMvDjQtCeOVhJdCuGV|FtGqF_ChGbLgH}WzZjb@sUpLpLrMdf@", "resource_state": 2}, "trainer": false, "commute": false, "manual": false, "private": false, "visibility": "everyone", "flagged": false, "gear_id": null, "start_latlng": [39.1, 16.08], "end_latlng": [40.0, 15.37], "average_speed": 7.384, "max_speed": 16.405, "average_temp": 24, "has_heartrate": true, "average_heartrate": 123.6, "max_heartrate": 157.0, "heartrate_opt_out": false, "display_hide_heartrate_option": true, "elev_high": 631.0, "elev_low": 2.0, "upload_id": 12248075854, "upload_id_str": "12248075854", "external_id": "garmin_ping_342339790734", "from_accepted_tag": false, "pr_count": 0, "total_photo_count": 5, "has_kudoed": false}, {"resource_state": 2, "athlete": {"id": 4495383, "resource_state": 1}, "name": "My Giro d\u2019Italia tappa 05: Sant Alessio - Amantea", "distance": 195148.0, "moving_time": 26730, "elapsed_time": 37557, "total_elevation_gain": 1701.0, "type": "Ride", "sport_type": "Ride", "workout_type": 10, "id": 11464496213, "start_date": "2024-05-21T06:14:54Z", "start_date_local": "2024-05-21T08:14:54Z", "timezone": "(GMT+01:00) Europe/Rome", "utc_offset": 7200.0, "location_city": null, "location_state": null, "location_country": "Germany", "achievement_count": 0, "kudos_count": 13, "comment_count": 2, "athlete_count": 1, "photo_count": 0, "map": {"id": "a11464496213", "summary_polyline": "kgnfFe_u|Aaj@yZyBoRyuB{lBsXqQiKpLoFaDrDiSaDqFm^o\\_CrLqHgB\\oS_aBovAgjAaqA{XcLab@oa@o`BwqBc_@hAmMgGkgBusBabA_bBqh@iLu_@cTmn@u`Ayv@qW{q@oh@_p@mOcb@mAyv@sa@kVeBue@{W_g@u_@c{AqZ_fAyh@gfEiuDwIvPmIfFwy@wE_d@qORmMiZ~H~L{gAxGciAI{o@oNyoAqWuw@ohAoqAdAsUlZoKmC]]kYy[u@ee@y^uE}MsBe^pBm`@oEiZqR{XkLkq@_QwPiJYqS}WgDoZ`BwO}PoZyDar@_IwP`G{MvBm[gOw`@mLkA|IgP`HarAaB}a@uWogA}Bwa@aScn@a_@al@{Nuj@yTqe@yk@cy@qPoaA_XcQoDiOoOcEmBvDjK{DcCoNtKjKmHyTrOlGcKsM]c^{Je@mJjJoNeH{`@uo@wAaK~JkXeJxEsGmVok@bd@eRc^nEm_AuDiLgj@xGgKxQud@nH}QsDqAuUad@_c@ah@g_@_S{XuWlBsDtPeN_i@qQ|We~@lBu`Asp@qZkb@aEuWm\\cd@obAuPe}@ih@c[pGuv@id@s]_r@cVcGmRqQgKc]erA_q@ktCogDmb@cv@sWsnAm^yTaWzKkM_B{CkMhBuZ}q@o~@qL~B}IiZ}iAcnAqd@q{@_L[mt@_a@kLwb@cx@unAqbAvOg`AkUcd@dAqc@ga@aL}_@{XaZ}S{E}GvGiZvAiEgSmQfFoN{CoXkUuf@ux@g{@wXs^rWkYrFt@`GoIqGzAjKcc@vPyK~T_Ntc@bCbL{IfD}s@a\\yVQgc@}b@i]cvAqb@_c@on@qeAnAya@~CoPuRsLoQsC]|H{ToFpCpDaCByh@e`@eHgS_[gVgEsXe@qQct@q`AoQkd@m_Ag`AkU}d@sq@if@eHgMZzL}IsQgPsKdLdRgLsP{Piu@qXs^wFsViz@yl@cs@w~@ef@ca@hHud@rFsF_E_IgVmGgM`a@sEvB}aB{`@yRyQsj@kOgzCsk@wcC_~AenEqf@qJuIms@g~Aas@g`@ki@e@sOdSeQb|AmR|{@aL`L{ZtAmXfSiJt\\iGtcB_z@zgAgX~wA_j@pfAa@puB_DrPsKxMgMdJk`A|P_w@f_@wNhRa}Abj@_{@ve@ctDfjDkvEnkAcRkIsC{Hwa@nIe@zGii@xRkpApO_Qf[qa@pE", "resource_state": 2}, "trainer": false, "commute": false, "manual": false, "private": false, "visibility": "everyone", "flagged": false, "gear_id": null, "start_latlng": [37.93, 15.35], "end_latlng": [39.1, 16.08], "average_speed": 7.301, "max_speed": 16.795, "average_temp": 24, "has_heartrate": true, "average_heartrate": 127.6, "max_heartrate": 169.0, "heartrate_opt_out": false, "display_hide_heartrate_option": true, "elev_high": 545.2, "elev_low": 0.4, "upload_id": 12240335531, "upload_id_str": "12240335531", "external_id": "garmin_ping_342109856978", "from_accepted_tag": false, "pr_count": 0, "total_photo_count": 8, "has_kudoed": false}, {"resource_state": 2, "athlete": {"id": 4495383, "resource_state": 1}, "name": "My Giro d\u2019Italia tappa 04b: Etna - St. Alesia", "distance": 72082.8, "moving_time": 9481, "elapsed_time": 18372, "total_elevation_gain": 686.0, "type": "Ride", "sport_type": "Ride", "workout_type": 10, "id": 11449418224, "start_date": "2024-05-19T10:36:48Z", "start_date_local": "2024-05-19T12:36:48Z", "timezone": "(GMT+01:00) Europe/Rome", "utc_offset": 7200.0, "location_city": null, "location_state": null, "location_country": "Germany", "achievement_count": 0, "kudos_count": 3, "comment_count": 0, "athlete_count": 1, "photo_count": 0, "map": {"id": "a11449418224", "summary_polyline": "ihbeFmlpzAtCqSdAkZu@oHiOoXNuJdF}U~@`@TzJvA@tDoUn@yJ`AE|@`Jz@iDwAuUj@iK}CuJB}HeDkPFmH_BsE~EeZgM}QnA{@`SzR`Es@nB{E_Cg]yE{BdFkGkDSgDaE]gLeDvDy@k@`BiHJyQxB{IIsExH~@x@mA{EsE}EiMrAqB|F_@jIgIO}AaHeG|Gi@cDcF`@kBtI\\sDsPvFtEhBw@sFiImHwDNiB`FeBjGuI_A}A_EtAcHoCxBcH_GaIhAmJe@mMnCsJ~GjApK{@dKcFdToC|FwCxCqKaDpCgF}@}EfAqGsCyFuJ{N{E~IW~DyB|NlC`CsJnLaNuQNwDgBiFfA_OkFcEcGyFp@dFmP^eTxAqRj@p@YoAZjA}LqGcKZaN}BmMuJsNc]q@_JuB}BeFbFkFl@`AgHoJzGgJiCoF`DkE}FqBC{O~HqHyJyCrEwPqAPrAcFfLuHs@gHzGcCeDuBhFaBd@yOo@sBsBmEvCyAiEwEbKgGiG_F|BmXLaPgEeJW_LsJ}DbBqGd@{DiD{ZaFwDyEmDAkKgHkHUiGuOcd@FqAkBf@sEuDoFib@aLmHg@eR`H}GiFmEsMcE_BF{HkGeFkJbAkSqCgFxDoFiBwM|BqC_J`S{GrJaIJkBeJ{An@{AvD^q@wBcLbAeVaDBqAxBAxEuGrBkHyAaC{DKaLfFoL[v@sE`Gt@zEkLlG`@`AiAuF{EQ{F{IaGe@mFlAsK`AwAjCRl@iBgBJsCuFbBoG_S~BgAsBmC`@ZqEqN_^mCwMOmHiCuAoCnDwAmFdCkRlVs]lByIoGkD_IuNbBoDlAa[pD{DsDwG@{BzCgBrDbFn@mGbD`DrGmC{JwOD{DuJa@_HiEbLE{GiRsAyUtCcFaBwHpBcCdi@uU~EuUyW{F_N{Ni]oj@r@cOqBcUeFuCi]}n@_Hm[mUy^aDkP_Ng]xAkg@sEeXgMaOyYwL}UeDsP_MwWo_@mLyI_E}ImBJsAyBiC|AcWwXcGyMg@eVjCaKw@wGdIyM{AmHeKrGuBWhBtA`IQsFpGkAkB{A`Ol@nCeAyH]`FRcIu@oC{CyA{AkEx@fHkC}GcEdBqE`GqJdSIlEjDfBCmJrEmQ_EjJcDvCyES}E|M}HuD{IBdHuAjGxBf@_Hk@}@oAnF{EcFqEXyFdIZ{H_AuJpBcHu@qDkTyDf@bAzFdAoSoOcJF_LgDyc@_ScPsJw_@mj@sR_SkKgRs\\ca@gX}U}FoJuRmMaFgReKcKmFoAgLgYaHsW}FwJ{I]yG|OlBuJgE~HwDZiW{IcIgJyW{RjBvA", "resource_state": 2}, "trainer": false, "commute": false, "manual": false, "private": false, "visibility": "everyone", "flagged": false, "gear_id": null, "start_latlng": [37.7, 15.0], "end_latlng": [37.93, 15.35], "average_speed": 7.603, "max_speed": 15.37, "average_temp": 22, "has_heartrate": true, "average_heartrate": 119.5, "max_heartrate": 165.0, "heartrate_opt_out": false, "display_hide_heartrate_option": true, "elev_high": 1912.6, "elev_low": 7.6, "upload_id": 12224781352, "upload_id_str": "12224781352", "external_id": "garmin_ping_341636896445", "from_accepted_tag": false, "pr_count": 0, "total_photo_count": 5, "has_kudoed": false}, {"resource_state": 2, "athlete": {"id": 4495383, "resource_state": 1}, "name": "My Giro d\u2018italia tappa 04a: Etna", "distance": 14920.8, "moving_time": 8442, "elapsed_time": 9892, "total_elevation_gain": 1200.0, "type": "Run", "sport_type": "TrailRun", "workout_type": 0, "id": 11445044062, "start_date": "2024-05-19T06:24:02Z", "start_date_local": "2024-05-19T08:24:02Z", "timezone": "(GMT+01:00) Europe/Rome", "utc_offset": 7200.0, "location_city": null, "location_state": null, "location_country": "Germany", "achievement_count": 1, "kudos_count": 10, "comment_count": 0, "athlete_count": 1, "photo_count": 0, "map": {"id": "a11445044062", "summary_polyline": "anbeFirpzAg@w@q@KwBhBoF[uB|AkBV{@^eAWcD^mC]k@LyBGcBLuCh@[\\yBUOPq@GKOoALwAh@y@RQ]SVi@SKTm@XMXULoARsArBgBAq@_@}Bo@gA}A_Am@e@Ga@k@QPOO[EcA?g@V{@MKJUEk@WUBGNk@HWSk@PYG_@o@{@g@mASuB_BSu@KsBAVmAO_@q@DYgAoAs@]k@?m@m@MTc@[g@Jo@Xy@vA}B?eBd@oCSmDaAgAl@gBTuCo@kBIWLGM_@Ra@IMNgBNOZDRQ?BPUFBNi@x@_@b@m@S[LYn@OjAY@g@l@kAUw@LCg@PtAc@Q_BEyARsBv@Ys@y@_@d@SFW_Ds@mBC{@s@{Be@e@@}AbCo@l@e@JcBM{@g@o@w@i@cBR`AKLS_CGOIFf@bBZh@WyBBs@n@qCz@cApAJjDlBVXVlBRd@?g@jAuDv@g@t@KtExAT\\Dx@NXe@fAuCnA{@DmDy@Ye@@Wr@mCj@kAsBgB_B{B}B}Ek@uBLcAdBkBlBRj@p@VFrCqBT[Ho@A_AUoABm@x@y@|BeAMeC[]Ow@UV[]NgCAiAq@L{BkBbBvBd@dAGXl@b@E|@bAbArAP`HIzFgCbHaCt@m@ZJXd@n@`CbBuBv@SvALv@`@jCLd@d@^MTg@PdCNb@|CrAbEvD~C|A`AlAx@~DfAGt@~@h@Bp@lAFX[|@l@lAn@hDf@jEPZX|A~@vAZdB@x@StAt@nCB`AYpAy@r@O^@~FZp@n@HpA}BZQf@Bp@XRd@o@rD@f@TVZKlAaCh@UVl@DpCf@^|@OdAeBZINLXbBV^ZEb@aBf@[NNRhA`@d@zAEzB~@dBe@xATZVXr@b@fEFjBHLXI`BmDZW`@NUjC[fADXVRj@GdAkAnCgAf@c@Xo@XiDP[b@@f@l@HnENPf@Iv@eFJyAQ}Aw@}BB{@XO^HlA`Ct@NxAER_@@W_@aAk@i@?a@b@IXNjAlBb@S[aCCsADmAf@iDImBTYND~@jBVCN_@x@gD\\kG|AeCCWk@[G[`AgAVK^H|@hAZjARLR_BbByAT_Bb@U`@l@bB`@x@z@lAl@\\H`AQRPPl@UjB`@dADf@f@v@WnAQN@b@f@DLR", "resource_state": 2}, "trainer": false, "commute": false, "manual": false, "private": false, "visibility": "everyone", "flagged": false, "gear_id": null, "start_latlng": [37.7, 15.0], "end_latlng": [37.7, 15.0], "average_speed": 1.767, "max_speed": 6.094, "average_cadence": 63.6, "average_temp": 23, "has_heartrate": true, "average_heartrate": 142.8, "max_heartrate": 158.0, "heartrate_opt_out": false, "display_hide_heartrate_option": true, "elev_high": 2937.0, "elev_low": 1910.4, "upload_id": 12220268624, "upload_id_str": "12220268624", "external_id": "garmin_ping_341551966027", "from_accepted_tag": false, "pr_count": 0, "total_photo_count": 5, "has_kudoed": false}, {"resource_state": 2, "athlete": {"id": 4495383, "resource_state": 1}, "name": "My\u00a0Giro d\u2019Italia tappa 03: Gangi - Etna", "distance": 112620.0, "moving_time": 18701, "elapsed_time": 21301, "total_elevation_gain": 2803.0, "type": "Ride", "sport_type": "Ride", "workout_type": 10, "id": 11439047715, "start_date": "2024-05-18T07:18:13Z", "start_date_local": "2024-05-18T09:18:13Z", "timezone": "(GMT+01:00) Europe/Rome", "utc_offset": 7200.0, "location_city": null, "location_state": null, "location_country": "Germany", "achievement_count": 0, "kudos_count": 8, "comment_count": 0, "athlete_count": 1, "photo_count": 0, "map": {"id": "a11439047715", "summary_polyline": "epteFs`vuAuBeGfErKsNrSdQcO|@wFmCcPcJqDaEqImEcw@bBaR_Beb@nKeG~DiQEaT}Kkp@uOyQxHkd@oUit@d@iQcF}^jSur@d_@i}@cEgRtEsJlFis@rLaZXoSlDaHhBuh@Xyb@jPiL_AiOdR{RzJgD`Ks\\fCi[h[yVzD_MxPg[zNlKpCtOjJsb@xLyDdAmNvDrGxQdBfSaf@lZxA~CjJj@{QsJsSno@yAvD{Eg@tKtJhCgChAaArLdHdFnFbQvLbExKjMvDoMbOfEnIeP}C{PtAsPxPuVpZmITaKuGeNJoK|H}LlP`JbPoFpObQbKKnMyHbBwMjTj@dUcT~BmKeFyIdBaQnLrCzEsKrGkHv[wAsFuLhKbB~EmGyFdAqGoHtI|BqHgLbGbDfFeBvP|KtYqCxQ|DlD}TlGmBt@kHrf@cZ~FsTxb@kPlDuFqAoHqLTlU_Ive@zOxd@wDtQhIkCwZbMwWm@{OqRoUgGeh@fKeOqF_T}Sc_@pDo[s@gKmGiJyE}X{L_CyHeNpFg_@lFsFbDwRB{W{QD}H{IvCeGwFaGWsSnEck@vQ_v@lAw_@vFmQeAmg@{CaBaDaQeHr@fKar@wCma@~GeZ`DgB_EEm@yEmCxJz@mMhJiGqIiILkVkKcVtk@oWw@qFfHqJ{DeDoAaCdI_RLkUcMsT@}[xFaLnLu{@wByC`Dq@fDwj@pCjBlAkPrO_KzBwNvPcIyAm`@fC}PuEwL_HgD|BwScJmRpRub@w@yH_Ej@uOcXu[ylBwE}G_Agi@~CkPbDed@sl@gw@qF{KoGe^bAyC{JcJjBkMqIw]`JkUqD_XbKa]gBcT|JoKpNm}@nGeP_Hc\\jIyOyAqT`GyGlAcQbFoDfCkWyCqc@gElAXiLzl@knB}Eur@uG{WqTee@aT{{@qNkKfMoNfDcXuWkXfHaGeSyFiBwGjH]WwG{YiDqJih@gXc@x@cQnFgHmUgSlOVnMsMnI|G}@uLs^yd@gNbC}H_FhJoFkD}BrNkFaQgZiM{IH}}A`EcFl@}IkLe_@_JmKyEuYqJeImPq@HuNwFuBv@{CsEiE{EsW`DyPvIwIbAoS{@sEvJmBzCu`@k@oY~MaSsC_JqIqFoQw[k@wI~GeU|S}AvCkSwByNiKeFoGwQyE\\bFs@iUDcMoPnAqHfDJjIwVwKkNkDt@s@sGdF_EfLl@zDaW_BrJ{GaBiCaGbDyLiEcEoK{@fBoPzHb@`BuKgSp@sUePnKqJbGuk@oBoCdDmI}As]fIkMa@gLnIqHaVaMoIwPJqJeCwDdDsl@}CL_Ph\\qCYnDuSoDq[sOgR", "resource_state": 2}, "trainer": false, "commute": false, "manual": false, "private": false, "visibility": "everyone", "flagged": false, "gear_id": null, "start_latlng": [37.79, 14.21], "end_latlng": [37.7, 15.0], "average_speed": 6.022, "max_speed": 18.516, "average_temp": 30, "has_heartrate": true, "average_heartrate": 144.7, "max_heartrate": 172.0, "heartrate_opt_out": false, "display_hide_heartrate_option": true, "elev_high": 1905.6, "elev_low": 212.4, "upload_id": 12214059747, "upload_id_str": "12214059747", "external_id": "garmin_ping_341362552032", "from_accepted_tag": false, "pr_count": 0, "total_photo_count": 7, "has_kudoed": false}, {"resource_state": 2, "athlete": {"id": 4495383, "resource_state": 1}, "name": "My Giro d\u2019Italia tappa 02: Palermo - Gangi", "distance": 129752.0, "moving_time": 21718, "elapsed_time": 26326, "total_elevation_gain": 2387.0, "type": "Ride", "sport_type": "Ride", "workout_type": 10, "id": 11432163976, "start_date": "2024-05-17T07:48:05Z", "start_date_local": "2024-05-17T09:48:05Z", "timezone": "(GMT+01:00) Europe/Rome", "utc_offset": 7200.0, "location_city": null, "location_state": null, "location_country": "Germany", "achievement_count": 0, "kudos_count": 10, "comment_count": 2, "athlete_count": 1, "photo_count": 0, "map": {"id": "a11432163976", "summary_polyline": "qtvgFiqnpAldAgk@aIee@~@oFjUaM{FkVx]e_@t]kO|RkWjFu^tk@ksBtLkjC`Nmm@jIat@~N}RvNum@mMajBsMa[lB{GsA_s@xJeTbGkd@sCcQdAy`@aOuOiAir@zC}Vxl@abAvXoNlF{ItI}QvD_`@fJfCjGvQ|LjO`PbFf\\sOn`@eNzMgUpa@i^x@ePnWal@tWwVrGaA`N}Tdk@ooBpNeTfTaGtBcOoDgHXaOeGsRnNkNl]ct@vq@_|@lIeZ|H_p@d@gc@jH{R~KaC`c@{w@xHgd@nRy`@Lk`AiAaX`Job@pHkB`LcWdLcOiGw@lBs\\vEgDiJqOu@kHhClA{FcFxFxBsD{E|GAqBkEbEaAcDwAdk@qY~OiYzMkkAbCezArEeMbPoMnCaLyCwbCpC_FnMwCzB{GcQ}aCaZy_Bvd@oZigCquJqAmwAiIkGhEjEvNsBrEjExMsGi@wGxMiPpHaBpDkTxIh@vHeM`N{Cda@qYjMbB`IkM|i@aCpE_FyAaQlPsFmB_K|A_LdO}E`E_K`OrDpFoCrUvQtNpCtT^hNiHdG}JtYsJnFwLxT}IvQe]bDw[jIcDIeHvEaGoAcGE_[oVwDyCeGfIuSkCqV|GrMBlIbAoH}CmJe@}ReNqG`YwYyFcDxBoKiLqIfC{LpNaSiIcXyGuG~ILtShSdPcC|JgOhP|C`Lw[yEwTrR}BjMkTqJyBt@yFmJuM|DmBcNKuH{HnJk[cJcEXcGlMq@nG|BhU~SkImUfKbFqDiG`EqTeBoJnVvRjBtH|TsTvPdBlKsF|KLwHbE|o@yAlZwKvDgX}BaHrDaAiC_EjLnBl@hHde@TtE|FmJm[{MgP}Nl@cEkO_Q]dMeBn@aIbHsAyAwGyGz@MiKqGqLzBkVr[aP~ZqEbQuNrBae@gHsLFwJvMcYna@iO|EyLhN_DfDkOcQm[mCko@wMcL_FcS_H{Ik@oPtC_S}Tcf@i@kQsL{MKiPlHyOr`@_FpJeLtDcTzSgK|FdBhErI|\\lEtI|Qhb@bg@`PxHhR{AdXxJhMQnEsGlTwAzHkIzR`@pLiH~EjBjT~]`JcDrLvCtGcF|DrDhIqEv@cGdE}AxGiRhFcElFmAxLxGbFaX|EiCxD{MtU_\\kBeWeNoOqd@tJgKgAsHuPoHo@qHq]}BgUdAiPcIaOmF_EaEmQwJwJiJoAsJ}_@gQwMmMkj@lOeTzLv@~JgG`VxEj^sO`ITdRcb@qSux@{OyAoU}MaFaNy@cQnCgI`NkJ^mJ|HoFE_LuHqSdAwMjBj@~CsWfM}Lrd@iEfW{^", "resource_state": 2}, "trainer": false, "commute": false, "manual": false, "private": false, "visibility": "everyone", "flagged": false, "gear_id": null, "start_latlng": [38.13, 13.35], "end_latlng": [37.79, 14.21], "average_speed": 5.974, "max_speed": 16.969, "average_temp": 27, "has_heartrate": true, "average_heartrate": 141.6, "max_heartrate": 166.0, "heartrate_opt_out": false, "display_hide_heartrate_option": true, "elev_high": 1621.6, "elev_low": 2.2, "upload_id": 12206968148, "upload_id_str": "12206968148", "external_id": "garmin_ping_341153502537", "from_accepted_tag": false, "pr_count": 0, "total_photo_count": 7, "has_kudoed": false}, {"resource_state": 2, "athlete": {"id": 4495383, "resource_state": 1}, "name": "My Giro d\u2019Italia tappa 01: Terrasini - Palermo", "distance": 38240.9, "moving_time": 5156, "elapsed_time": 5383, "total_elevation_gain": 208.0, "type": "Ride", "sport_type": "Ride", "workout_type": 10, "id": 11425860900, "start_date": "2024-05-16T16:03:39Z", "start_date_local": "2024-05-16T18:03:39Z", "timezone": "(GMT+01:00) Europe/Rome", "utc_offset": 7200.0, "location_city": null, "location_state": null, "location_country": "Germany", "achievement_count": 0, "kudos_count": 12, "comment_count": 1, "athlete_count": 1, "photo_count": 0, "map": {"id": "a11425860900", "summary_polyline": "ooahFob_oAu@iB]]eCu@YLOZUPMCKY_@iDFsAAm@M_AaGaWuA_Ie@yFCwFd@wKCmBDoBf@uCNYv@e@jDiE`AwBjBoFp@iC`@{BL}@CsAb@wAtAuKb@eCb@oBt@{BnA{ChOoW~AiDdAaDf@qCSkB@gAHaAPg@Z_@r@gB`BqQOw@k@CU[MeD@yApDoLtHuX~Im]nAaEp@aDb@cDdCaFPyATq@VUn@ElGP`@ChF_AxBOjB_@vAg@`EqCtE{Ez@e@RUt@{Ax@wBt@eDZmBVwFCcWNc@fCX`RdAt\\jDx@PfAd@l@~AJHJK~@mCn@mG~@_ILkD_@sGBgBZoDEcNOyAyAqF[cC]yQ@gBNiEA_BMy@kBkG}AcJG{AByATqBz@}Cx@yBhGwJZcAl@cDNkBG_Ak@yCiBiGk]msAsBgHuJoZwDwMsBaGk@}BwAmHi@qBs@sAiB{B]sA@y@GYs@k@Wo@s@aE[eAw@}AoByBm@}Ae@kBKmAAmDXwRJqQTqCCUIU}CoCiDuAiDgA}Aw@oRkLcOwJuHqH{IuHoA{@yAi@mBa@aMgAuAi@_GgDoDsAsKyByUcEgE_BcEmCqE_By@iAm@}Ck@eB}J_POg@Ak@Fe@jBmFp@iDNkDVuNMcEUkBe@uAy@oAqCeCwCoEQk@?a@Tk@`@SbEUvAg@dKsOKPPk@R}Fc@qGRSfBi@PKBQwB{H]m@VFlHiKdDqHfB_DF[?yEPwAn@eCbAoCrAuChCiHzBuFhEoLfNk`@ZwAN{A?iNl@cCdAsBRu@Aa@Ma@kBgBM[E_@B}`@FmICea@DwC`@yBC]Wm@IsAAib@LmAd@gCCUk@UO[c@cJmD{f@]mD?m@HYhAmADUYWe@@}f@jEi@Bc@UWa@?]vAyEV}BbDWTMBSeAyUCwCXwAr@mA`@[|GcBlAaAfSi^b@aAzCcF`@gATcCr@qQ@qDQ_BUeAqAiFi@}AcBiCmF}GWk@Mi@G_AFeAh@}Ah@o@rHaDnM}FfBaBpOgPjCaCvDqBjDsApNiDbBEfFf@xP_@`LTbBYtD_BpBSbFZdTxCz@A\\]Lm@Ai@k@mEPsFR{@JOdGaCrYcKZ@vErBtR`BdBDn`@y@xDArAL~NlDvAfARt@?l@cAfDD`@RVh@FhAU`AEfBzAnAn@~HpAXE|E{B~A_@bAK|FEXBVPTz@nBdN^nBlCfQT|@hCjQzEzZ|@tEz@tGv@bEzCrR", "resource_state": 2}, "trainer": false, "commute": false, "manual": false, "private": false, "visibility": "everyone", "flagged": false, "gear_id": null, "start_latlng": [38.19, 13.11], "end_latlng": [38.13, 13.35], "average_speed": 7.417, "max_speed": 13.313, "average_temp": 22, "has_heartrate": true, "average_heartrate": 126.7, "max_heartrate": 158.0, "heartrate_opt_out": false, "display_hide_heartrate_option": true, "elev_high": 49.6, "elev_low": 3.2, "upload_id": 12200480433, "upload_id_str": "12200480433", "external_id": "garmin_ping_340949612749", "from_accepted_tag": false, "pr_count": 0, "total_photo_count": 4, "has_kudoed": false}]